Workbook
Name Selling_Price: '[1]Base Case'!$B$11
Name taxtable: #REF!
Name Variable_Cost_per_unit: '[1]Base Case'!$B$12

Sheet ULTA Forecast
B2: Final Project. Forecasted Financial Statements and Comparative Analysis
B3: Proejct Company: ULTA Beauty
B4: Financial Analyst: Carolina Galindo Mendoza
B6: Part I. Assumption Table ($ thousand, %) | E6: Forecasted –—>
B8: 1. Forecasting Assumptions. | D8: 2026 FYQ3 Actual | E8: 2026 FYQ4 | F8: 2027 FYQ1 | G8: 2027 FYQ2 | H8: 2027 FYQ3 | I8: 2027 FYQ4
B9: Comprehensive Income Statement items
B10: Sales forecasted ($ thousands) | D10: =D44 -> 2857623 | E10: ='ULTA HWAS'!G96*0.95 -> 2868908 | F10: ='ULTA HWAS'!G97*0.95 -> 2787071.6 | G10: ='ULTA HWAS'!G98*0.95 -> 2837762.6 | H10: ='ULTA HWAS'!G99*0.95 -> 3758455.9 | I10: ='ULTA HWAS'!G100*0.95 -> 3095924.9
B11: Cost of Sales ($ in tousands) | D11: =D45 -> -1701958 | E11: =-'ULTA %Sales & Trend'!H88 -> -1781573.7 | F11: =-'ULTA %Sales & Trend'!H89 -> -1815657.7 | G11: =-'ULTA %Sales & Trend'!H90 -> -1823232 | H11: =-'ULTA %Sales & Trend'!H91 -> -1849741.8 | I11: =-'ULTA %Sales & Trend'!H92 -> -1880309.2
B12: Total Operating Exp. ($ in tousands) | D12: =D48 -> -840920 | E12: =-'ULTA %Sales & Trend'!G88 -> -786354.46 | F12: =-'ULTA %Sales & Trend'!G89 -> -805786.25 | G12: =-'ULTA %Sales & Trend'!G90 -> -810104.42 | H12: =-'ULTA %Sales & Trend'!G91 -> -825218.04 | I12: =-'ULTA %Sales & Trend'!G92 -> -842644.96
B13: Other (Non-Operating) Expenses ($ in tousands) | D13: =D50 -> -9449 | E13: ='ULTA %Sales & Trend'!F88 -> -3197.8453 | F13: ='ULTA %Sales & Trend'!F89 -> -3056.1185 | G13: ='ULTA %Sales & Trend'!F90 -> -3024.6237 | H13: ='ULTA %Sales & Trend'!F91 -> -2914.3917 | I13: ='ULTA %Sales & Trend'!F92 -> -2787.2876
B14: Income tax ($ in thousands) | D14: =D52 -> -73436 | E14: =-'ULTA %Sales & Trend'!E88 -> -98039.974 | F14: =-'ULTA %Sales & Trend'!E89 -> -99978.009 | G14: =-'ULTA %Sales & Trend'!E90 -> -100408.68 | H14: =-'ULTA %Sales & Trend'!E91 -> -101916.04 | I14: =-'ULTA %Sales & Trend'!E92 -> -103654.12
B15: Equity net loss of affiliate ($ in thousands) | D15: =D54 -> -985 | E15: =AVERAGE($D$15,-597,-628) -> -736.66667 | F15: =AVERAGE($D$15,-597,-628) -> -736.66667 | G15: =AVERAGE($D$15,-597,-628) -> -736.66667 | H15: =AVERAGE($D$15,-597,-628) -> -736.66667 | I15: =AVERAGE($D$15,-597,-628) -> -736.66667
B16: Balance Sheet accounts
B17: Property, plant and equipment, net | D17: ='ULTA %Sales & Trend'!I87 -> 3077308 | E17: ='ULTA %Sales & Trend'!I88 -> 3042601.1 | F17: ='ULTA %Sales & Trend'!I89 -> 3103816.3 | G17: ='ULTA %Sales & Trend'!I90 -> 3117419.6 | H17: ='ULTA %Sales & Trend'!I91 -> 3165031.4 | I17: ='ULTA %Sales & Trend'!I92 -> 3219930.7
B18: Depreciation | D18: 0 | E18: =-((2153831)+171068.5) -> -2324899.5 | F18: 0 | G18: 0 | H18: 0 | I18: =E18-171068.5 -> -2495968
B19: Depreciation (% of fixed assets) | D19: 0 | E19: =E18/(E17-E18) -> -0.43314378 | F19: =F18/(F17-F18) -> 0 | G19: =G18/(G17-G18) -> 0 | H19: =H18/(H17-H18) -> 0 | I19: =I18/(I17-I18) -> -0.43667114
B20: Cash (% avg. YoY rate) | D20: 0.033 | E20: -0.0146 | F20: -0.1122 | G20: -0.1511 | H20: 0.0327 | I20: -0.0146
B21: Cash ($ in thousands) | D21: =D61 -> 204921 | E21: =(703201)*(1+E20) -> 692934.27 | F21: =454629*(1+F20) -> 403619.63 | G21: =242745*(1+G20) -> 206066.23 | H21: =204921*(1+H20) -> 211621.92 | I21: =692934*(1+I20) -> 682817.16
B22: Inventories (% of Growth) | D22: 0.1399 | E22: 0.08 | F22: 0.1 | G22: 0.12 | H22: 0.135 | I22: 0.08
B23: Debt-to-Equity ratio (D/E) | D23: =D87/D97 -> 0.65788446 | E23: 0.65 | F23: 0.65 | G23: 0.64 | H23: 0.64 | I23: 0.63
B24: Prepaid income taxes (% of EBIT) | D24: =D65/D49 -> 0.084083941 | E24: 0.1 | F24: 0 | G24: 0.085 | H24: 0.09 | I24: 0.11
B25: Goodwill ($ in thousands) | D25: 392606 | E25: =D25 -> 392606 | F25: =E25 -> 392606 | G25: =F25 -> 392606 | H25: =G25 -> 392606 | I25: =H25 -> 392606
B26: Other intangible assets, net ($ in thousands) | D26: =D73 -> 6089 | E26: =D26+(D26*1.5%) -> 6180.335 | F26: 0 | G26: 5500 | H26: 6050 | I26: 6150
B27: Accounts Payable (as % of inventory) | D27: =D79/D62 -> 0.27664026 | E27: 0.27 | F27: 0.27 | G27: 0.27 | H27: 0.27 | I27: 0.27
B28: Accrued liabilities (as % of Operating Exp.) | D28: =D80/-D48 -> 0.56360772 | E28: 0.52 | F28: 0.52 | G28: 0.52 | H28: 0.52 | I28: 0.52
B29: Deferred revenue (% of growth) | D29: 0.0094 | E29: 0.005 | F29: 0.005 | G29: 0.005 | H29: 0.005 | I29: 0.005
B30: Accrude income taxes (% of Income Tax Exp.) | D30: =D83/D52 -> 0 | E30: 0.25 | F30: 1 | G30: 0 | H30: 0 | I30: 0.25
B31: Short-term debt ($ in thousands) | D31: =D84 -> 551721 | E31: 0 | F31: 0 | G31: 289101 | H31: 551721 | I31: 0
B32: Other long-term liabilities (% of growth) | D32: 0.0439 | E32: 0.04 | F32: 0.0375 | G32: 0.035 | H32: 0.0325 | I32: 0.03
B33: Common stock (QoQ value change) | D33: -4 | E33: -5.49 | F33: -5.49 | G33: -5.49 | H33: -5.49 | I33: -5.49
B34: Treasury Stock-common, at cost (QoQ value change) | D34: -267 | E34: -4776.68 | F34: -4776.68 | G34: -4776.68 | H34: -4776.68 | I34: -4776.68
B35: Non-current operating lease liabilities (% of growth) | D35: 0.0094 | E35: 0.015 | F35: 0.015 | G35: 0.015 | H35: 0.015 | I35: 0.015
B36: Additional paid-in capital (QoQ value change) | D36: 23264 | E36: 12986.85 | F36: 12986.85 | G36: 12986.85 | H36: 12986.85 | I36: 12986.85
B37: Retained earnings (% of growth) | D37: 0.0039 | E37: 0.05 | F37: 0.05 | G37: 0.05 | H37: 0.05 | I37: 0.05
B41: Part II. Financial Planning with Forecasted Financial Statements ($ thousand) | E41: Forecasted –—>
B43: 1. Income Statement for the quarter ended | C43: % of sales | D43: 2026 FYQ3 Actual | E43: 2026 FYQ4 | F43: 2027 FYQ1 | G43: 2027 FYQ2 | H43: 2027 FYQ3 | I43: 2027 FYQ4
B44: Total net sales | C44: =D44/$D$44 -> 1 | D44: ='ULTA Q Rev (Acual)'!C87 -> 2857623 | E44: =E10 -> 2868908 | F44: =F10 -> 2787071.6 | G44: =G10 -> 2837762.6 | H44: =H10 -> 3758455.9 | I44: =I10 -> 3095924.9
B45: Less Cost of sales | C45: =D45/$D$44 -> -0.59558521 | D45: -1701958 | E45: =E11 -> -1781573.7 | F45: =F11 -> -1815657.7 | G45: =G11 -> -1823232 | H45: =H11 -> -1849741.8 | I45: =I11 -> -1880309.2
B46: Gross profit | C46: =D46/$D$44 -> 0.40441479 | D46: =D44+D45 -> 1155665 | E46: =E44+E45 -> 1087334.4 | F46: =F44+F45 -> 971413.82 | G46: =G44+G45 -> 1014530.6 | H46: =H44+H45 -> 1908714.1 | I46: =I44+I45 -> 1215615.7
B47: Less Operating expenses:
B48: Total Operating Expenses | C48: =D48/$D$44 -> -0.29427255 | D48: -840920 | E48: =E12 -> -786354.46 | F48: =F12 -> -805786.25 | G48: =G12 -> -810104.42 | H48: =H12 -> -825218.04 | I48: =I12 -> -842644.96
B49: Operating Profit | C49: =D49/$D$44 -> 0.11014224 | D49: =D46+D48 -> 314745 | E49: =E46+E48 -> 300979.89 | F49: =F46+F48 -> 165627.57 | G49: =G46+G48 -> 204426.17 | H49: =H46+H48 -> 1083496.1 | I49: =I46+I48 -> 372970.7
B50: Other (Non-Operating) Expenses | C50: =D50/$D$44 -> -0.0033065943 | D50: -9449 | E50: =E13 -> -3197.8453 | F50: =F13 -> -3056.1185 | G50: =G13 -> -3024.6237 | H50: =H13 -> -2914.3917 | I50: =I13 -> -2787.2876
B51: Pretax Income | C51: =D51/$D$44 -> 0.10683565 | D51: =D49+D50 -> 305296 | E51: =SUM(E49:E50) -> 297782.05 | F51: =SUM(F49:F50) -> 162571.45 | G51: =SUM(G49:G50) -> 201401.55 | H51: =SUM(H49:H50) -> 1080581.7 | I51: =SUM(I49:I50) -> 370183.41
B52: Less Income tax | C52: =D52/$D$44 -> -0.025698281 | D52: -73436 | E52: =E14 -> -98039.974 | F52: =F14 -> -99978.009 | G52: =G14 -> -100408.68 | H52: =H14 -> -101916.04 | I52: =I14 -> -103654.12
B53: Income before equity net loss of affiliate | C53: =D53/$D$44 -> 0.081137365 | D53: =D51+D52 -> 231860 | E53: =E51+E52 -> 199742.07 | F53: =F51+F52 -> 62593.442 | G53: =G51+G52 -> 100992.86 | H53: =H51+H52 -> 978665.66 | I53: =I51+I52 -> 266529.29
B54: Less equity net loss of affiliate | C54: =D54/$D$44 -> -0.00034469207 | D54: -985 | E54: =E15 -> -736.66667 | F54: =F15 -> -736.66667 | G54: =G15 -> -736.66667 | H54: =H15 -> -736.66667 | I54: =I15 -> -736.66667
B55: Net Income (Profit after tax) | C55: =D55/$D$44 -> 0.080792673 | D55: =D53+D54 -> 230875 | E55: =E53+E54 -> 199005.41 | F55: =F53+F54 -> 61856.776 | G55: =G53+G54 -> 100256.2 | H55: =H53+H54 -> 977929 | I55: =I53+I54 -> 265792.62
B59: 2. Balance sheet (B/S), as of quarter end | C59: % of sales | D59: 2026 FYQ3 Actual | E59: 2026 FYQ4 | F59: 2027 FYQ1 | G59: 2027 FYQ2 | H59: 2027 FYQ3 | I59: 2027 FYQ4
B60: Current assets:
B61: Cash and cash equivalents | C61: =D61/$D$44 -> 0.071710299 | D61: 204921 | E61: =E21 -> 692934.27 | F61: =F21 -> 403619.63 | G61: =G21 -> 206066.23 | H61: =H21 -> 211621.92 | I61: =I21 -> 682817.16
B62: Merchandise inventories, net | C62: =D62/$D$44 -> 0.9601123 | D62: 2743639 | E62: =(E22*D62)+D62 -> 2963130.1 | F62: =(F22*E62)+E62 -> 3259443.1 | G62: =(G22*F62)+F62 -> 3650576.3 | H62: =(H22*G62)+G62 -> 4143404.1 | I62: =(I22*H62)+H62 -> 4474876.4
B63: Receivables, net | C63: =D63/$D$44 -> 0.083059242 | D63: 237352 | E63: =$C$63*E44 -> 238289.33 | F63: =$C$63*F44 -> 231492.05 | G63: =$C$63*G44 -> 235702.41 | H63: =$C$63*H44 -> 312174.5 | I63: =$C$63*I44 -> 257145.17
B64: Prepaid expenses and other current assets | C64: =D64/$D$44 -> 0.055428585 | D64: 158394 | E64: =D64 -> 158394 | F64: =E64 -> 158394 | G64: =G77-G76-G65-G63-G62-G61 -> 2204258.3 | H64: =G64 -> 2204258.3 | I64: =I77-I76-I65-I63-I62-I61 -> 6530147.4
B65: Prepaid income taxes | C65: =D65/$D$44 -> 0.0092611937 | D65: 26465 | E65: =E24*E49 -> 30097.989 | F65: =F24*F49 -> 0 | G65: =G24*G49 -> 17376.224 | H65: =H24*H49 -> 97514.649 | I65: =I24*I49 -> 41026.777
B66: Total current assets | C66: =D66/$D$44 -> 1.1795716 | D66: =SUM(D61:D65) -> 3370771 | E66: =SUM(E61:E65) -> 4082845.7 | F66: =SUM(F61:F65) -> 4052948.8 | G66: =SUM(G61:G65) -> 6313979.5 | H66: =SUM(H61:H65) -> 6968973.5 | I66: =SUM(I61:I65) -> 11986013
B67: Non-current assets:
B68: Gross Property, Plant and Equipment | C68: =D68/$D$44 -> 0 | D68: 0 | E68: =E70+E69 -> 717701.62 | F68: =F70+F69 -> 3103816.3 | G68: =G70+G69 -> 3117419.6 | H68: =H70+H69 -> 3165031.4 | I68: =I70+I69 -> 723962.68
B69: Less Total Accumulated Depreciation and Impairment | C69: =D69/$D$44 -> 0 | D69: 0 | E69: =E18 -> -2324899.5 | F69: =F18 -> 0 | G69: =G18 -> 0 | H69: =H18 -> 0 | I69: =I18 -> -2495968
B70: Net Property, Plant and Equipment | C70: =D70/$D$44 -> 0.47819604 | D70: 1366504 | E70: =E17 -> 3042601.1 | F70: =F17 -> 3103816.3 | G70: =G17 -> 3117419.6 | H70: =H17 -> 3165031.4 | I70: =I17 -> 3219930.7
B71: Operating lease assets | C71: =D71/$D$44 -> 0.59868079 | D71: 1710804 | E71: =$C$71*E44 -> 1717560.1 | F71: =$C$71*F44 -> 1668566.2 | G71: =$C$71*G44 -> 1698913.9 | H71: =$C$71*H44 -> 2250115.4 | I71: =$C$71*I44 -> 1853470.8
B72: Goodwill | C72: =D72/$D$44 -> 0.13738901 | D72: 392606 | E72: =E25 -> 392606 | F72: =F25 -> 392606 | G72: =G25 -> 392606 | H72: =H25 -> 392606 | I72: =I25 -> 392606
B73: Other intangible assets, net | C73: =D73/$D$44 -> 0.0021307919 | D73: 6089 | E73: =$C$73*E44 -> 6113.0461 | F73: =$C$73*F44 -> 5938.6695 | G73: =$C$73*G44 -> 6046.6815 | H73: =$C$73*H44 -> 8008.4875 | I73: =$C$73*I44 -> 6596.7717
B74: Deferred compensation plan assets | C74: =D74/$D$44 -> 0.018436302 | D74: 52684 | E74: =$C$74*E44 -> 52892.054 | F74: =$C$74*F44 -> 51383.292 | G74: =$C$74*G44 -> 52317.847 | H74: =$C$74*H44 -> 69292.028 | I74: =$C$74*I44 -> 57077.406
B75: Other long-term assets | C75: =D75/$D$44 -> 0.039485265 | D75: 112834 | E75: =$C$75*E44 -> 113279.59 | F75: =$C$75*F44 -> 110048.26 | G75: =$C$75*G44 -> 112049.81 | H75: =$C$75*H44 -> 148403.63 | I75: =$C$75*I44 -> 122243.41
B76: Total non-current assets | D76: =SUM(D68:D75) -> 3641521 | E76: =SUM(E68:E75) -> 3717854.1 | F76: =SUM(F68:F75) -> 8436174.9 | G76: =SUM(G68:G75) -> 8496773.5 | H76: =SUM(H68:H75) -> 9198488.3 | I76: =SUM(I68:I75) -> 3879919.7
B77: Total assets | C77: =D77/$D$44 -> 2.4538898 | D77: =D76+D66 -> 7012292 | E77: =E76+E66 -> 7800699.8 | F77: =F76+F66 -> 12489124 | G77: =G98 -> 14810753 | H77: =H76+H66 -> 16167462 | I77: =I98 -> 15865933
B78: Current liabilities:
B79: Accounts payable | C79: =D79/$D$44 -> 0.26560571 | D79: 759001 | E79: =E27*E62 -> 800045.13 | F79: =F27*F62 -> 880049.65 | G79: =G27*G62 -> 985655.6 | H79: =H27*H62 -> 1118719.1 | I79: =I27*I62 -> 1208216.6
B80: Accrued liabilities | C80: =D80/$D$44 -> 0.16585428 | D80: 473949 | E80: =E28*-E48 -> 408904.32 | F80: =F28*-F48 -> 419008.85 | G80: =G28*-G48 -> 421254.3 | H80: =H28*-H48 -> 429113.38 | I80: =I28*-I48 -> 438175.38
B81: Deferred revenue | C81: =D81/$D$44 -> 0.16201017 | D81: 462964 | E81: =(E29*D81)+D81 -> 465278.82 | F81: =(F29*E81)+E81 -> 467605.21 | G81: =(G29*F81)+F81 -> 469943.24 | H81: =(H29*G81)+G81 -> 472292.96 | I81: =(I29*H81)+H81 -> 474654.42
B82: Current operating lease liabilities | C82: =D82/$D$44 -> 0.1017335 | D82: 290716 | E82: =E98-E97-E83-E84-E81-E80-E79 -> 3381856 | F82: =F98-F97-F83-F84-F81-F80-F79 -> 7811340.7 | G82: =F82 -> 7811340.7 | H82: =H98-H97-H90-H83-H84-H81-H80-H79 -> 8618561.1 | I82: =H82 -> 8618561.1
B83: Accrude income taxes | C83: =D83/$D$44 -> 0 | D83: 0 | E83: =E30*-E52 -> 24509.993 | F83: =F30*-F52 -> 99978.009 | G83: =G30*-G52 -> 0 | H83: =H30*-H52 -> 0 | I83: =I30*-I52 -> 25913.531
B84: Short-term debt | C84: =D84/$D$44 -> 0.1930699 | D84: 551721 | E84: =E31 -> 0 | F84: =F31 -> 0 | G84: =G31 -> 289101 | H84: =H31 -> 551721 | I84: =I31 -> 0
B85: Total current liabilities | C85: =D85/$D$44 -> 0.88827358 | D85: =SUM(D79:D84) -> 2538351 | E85: =SUM(E79:E84) -> 5080594.3 | F85: =SUM(F79:F84) -> 9677982.4 | G85: =SUM(G79:G84) -> 9977294.9 | H85: =SUM(H79:H84) -> 11190408 | I85: =SUM(I79:I84) -> 10765521
B86: Non-current liabilities:
B87: Non-current operating lease liabilities | C87: =D87/$D$44 -> 0.60617478 | D87: 1732219 | E87: =(E35*D87)+D87 -> 1758202.3 | F87: =(F35*E87)+E87 -> 1784575.3 | G87: =(G35*F87)+F87 -> 1811343.9 | H87: =(H35*G87)+G87 -> 1838514.1 | I87: =(I35*H87)+H87 -> 1866091.8
B88: Deferred income taxes | C88: =D88/$D$44 -> 0.015856535 | D88: 45312 | E88: =$C$88*E44 -> 45490.942 | F88: =$C$88*F44 -> 44193.298 | G88: =$C$88*G44 -> 44997.082 | H88: =$C$88*H44 -> 59596.089 | I88: =$C$88*I44 -> 49090.642
B89: Other long-term liabilities | C89: =D89/$D$44 -> 0.022184872 | D89: 63396 | E89: =D89*(1+E32) -> 65931.84 | F89: =E89*(1+F32) -> 68404.284 | G89: =F89*(1+G32) -> 70798.434 | H89: =G89*(1+H32) -> 73099.383 | I89: =H89*(1+I32) -> 75292.365
B90: Total non-current liabilities | D90: =SUM(D87:D89) -> 1840927 | E90: =SUM(E87:E89) -> 1869625.1 | F90: =SUM(F87:F89) -> 1897172.9 | G90: =SUM(G87:G89) -> 1927139.5 | H90: =SUM(H87:H89) -> 1971209.6 | I90: =SUM(I87:I89) -> 1990474.8
B91: Total liabilities | C91: =D91/$D$44 -> 1.5324898 | D91: =D85+D90 -> 4379278 | E91: =E85+E90 -> 6950219.4 | F91: =F85+F90 -> 11575155 | G91: =G85+G90 -> 11904434 | H91: =H85+H90 -> 13161617 | I91: =I85+I90 -> 12755996
B92: Shareholder's Equity:
B93: Common stock | C93: =D93/$D$44 -> 0.0001588733 | D93: 454 | E93: =D93+E33 -> 448.51 | F93: =E93+F33 -> 443.02 | G93: =F93+G33 -> 437.53 | H93: =G93+H33 -> 432.04 | I93: =H93+I33 -> 426.55
B94: Treasury Stock-common, at cost | C94: =D94/$D$44 -> -0.042097226 | D94: -120298 | E94: =D94+(E34) -> -125074.68 | F94: =E94+(F34) -> -129851.36 | G94: =F94+(G34) -> -134628.04 | H94: =G94+(H34) -> -139404.72 | I94: =H94+(I34) -> -144181.4
B95: Additional paid-in capital | C95: =D95/$D$44 -> 0.41122359 | D95: 1175122 | E95: =D95+E36 -> 1188108.9 | F95: =E95+F36 -> 1201095.7 | G95: =F95+G36 -> 1214082.6 | H95: =G95+H36 -> 1227069.4 | I95: =H95+I36 -> 1240056.3
B96: Retained earnings | C96: =D96/$D$44 -> 0.55211482 | D96: 1577736 | E96: =(E37*D96)+D96 -> 1656622.8 | F96: =(F37*E96)+E96 -> 1739453.9 | G96: =(G37*F96)+F96 -> 1826426.6 | H96: =(H37*G96)+G96 -> 1917748 | I96: =(I37*H96)+H96 -> 2013635.4
B97: Total Shareholders’ Equity | C97: =D97/$D$44 -> 0.92140006 | D97: =SUM(D93:D96) -> 2633014 | E97: =SUM(E93:E96) -> 2720105.5 | F97: =SUM(F93:F96) -> 2811141.3 | G97: =SUM(G93:G96) -> 2906318.7 | H97: =SUM(H93:H96) -> 3005844.7 | I97: =SUM(I93:I96) -> 3109936.8
B98: Total liabilities and shareholders' equity | C98: =D98/$D$44 -> 2.4538898 | D98: =D91+D97 -> 7012292 | E98: =E77 -> 7800699.8 | F98: =F77 -> 12489124 | G98: =G97+G91 -> 14810753 | H98: =H77 -> 16167462 | I98: =I97+I91 -> 15865933
B102: 3. Statement of Cash Flows, for the quarter ended | E102: 2026 FYQ4 | F102: 2027 FYQ1 | G102: 2027 FYQ2 | H102: 2027 FYQ3 | I102: 2027 FYQ4
B103: Operating:
B104: Net Income | E104: =E55 -> 199005.41 | F104: =F55 -> 61856.776 | G104: =G55 -> 100256.2 | H104: =H55 -> 977929 | I104: =I55 -> 265792.62
B105: Depreciation and amortization | E105: =-D69 -> 0 | F105: =-E69 -> 2324899.5 | G105: =-F69 -> 0 | H105: =-G69 -> 0 | I105: =-H69 -> 0
B106: Deferred income taxes | E106: =E88 -> 45490.942 | F106: =F88 -> 44193.298 | G106: =G88 -> 44997.082 | H106: =H88 -> 59596.089 | I106: =I88 -> 49090.642
B107: Change in Receivable | E107: =E63-D63 -> 937.32645 | F107: =F63-E63 -> -6797.2762 | G107: =G63-F63 -> 4210.3567 | H107: =H63-G63 -> 76472.093 | I107: =I63-H63 -> -55029.326
B108: Change in Merchandise inventories | E108: =E62-D62 -> 219491.12 | F108: =F62-E62 -> 296313.01 | G108: =G62-F62 -> 391133.18 | H108: =H62-G62 -> 492827.8 | I108: =I62-H62 -> 331472.33
B109: Change in Prepaid expenses and other current assets | E109: =E64-D64 -> 0 | F109: =F64-E64 -> 0 | G109: =G64-F64 -> 2045864.3 | H109: =H64-G64 -> 0 | I109: =I64-H64 -> 4325889.1
B110: Change in Income taxes | E110: =E65-D65 -> 3632.9893 | F110: =F65-E65 -> -30097.989 | G110: =G65-F65 -> 17376.224 | H110: =H65-G65 -> 80138.425 | I110: =I65-H65 -> -56487.872
B111: Change in accounts payable | E111: =E79-D79 -> 41044.132 | F111: =F79-E79 -> 80004.513 | G111: =G79-F79 -> 105605.96 | H111: =H79-G79 -> 133063.51 | I111: =I79-H79 -> 89497.529
B112: Change in Accrued liabilities | E112: =E80-D80 -> -65044.679 | F112: =F80-E80 -> 10104.529 | G112: =G80-F80 -> 2245.4509 | H112: =H80-G80 -> 7859.0781 | I112: =I80-H80 -> 9061.9982
B113: Change in other assets and liabilties | E113: =E89-D89 -> 2535.84 | F113: =F89-E89 -> 2472.444 | G113: =G89-F89 -> 2394.1499 | H113: =H89-G89 -> 2300.9491 | I113: =I89-H89 -> 2192.9815
...

Sheet ULTA Q Rev (Acual)
A2: ULTA Beauty Quarterly Sales (Actual)
A4: Fiscal Q | B4: Date | C4: Q Sales | D4: Y Sales | H4: ="Apple Quarterly Sales"&CHAR(10)&" "&TEXT(B5,"mmm yyyy")&" to "&TEXT(B86,"mmm yyyy") -> Apple Quarterly Sales Apr 2005 to Aug 2025
A5: FQ 1Q06 | B5: 38472 | C5: 144769
A6: FQ 2Q06 | B6: 38564 | C6: 144769
A7: FQ 3Q06 | B7: 38656 | C7: 144769
A8: FQ 4Q06 | B8: 38748 | C8: 144768 | D8: =SUM(C5:C8) -> 579075
A9: FQ 1Q07 | B9: 38837 | C9: 159468
A10: FQ 2Q07 | B10: 38929 | C10: 162558
A11: FQ 3Q07 | B11: 39021 | C11: 216544
A12: FQ 4Q07 | B12: 39113 | C12: 216543 | D12: =SUM(C9:C12) -> 755113
A13: FQ 1Q08 | B13: 39202 | C13: 194113
A14: FQ 2Q08 | B14: 39293 | C14: 200449
A15: FQ 3Q08 | B15: 39386 | C15: 208235
A16: FQ 4Q08 | B16: 39478 | C16: 309344 | D16: =SUM(C13:C16) -> 912141
A17: FQ 1Q09 | B17: 39568 | C17: 239298
A18: FQ 2Q09 | B18: 39660 | C18: 249111
A19: FQ 3Q09 | B19: 39752 | C19: 254843
A20: FQ 4Q09 | B20: 39844 | C20: 341394 | D20: =SUM(C17:C20) -> 1084646
A21: FQ 1Q10 | B21: 39933 | C21: 268825
A22: FQ 2Q10 | B22: 40025 | C22: 273539
A23: FQ 3Q10 | B23: 40117 | C23: 284043
A24: FQ 4Q10 | B24: 40209 | C24: 396364 | D24: =SUM(C21:C24) -> 1222771
A25: FQ 1Q11 | B25: 40298 | C25: 320196
A26: FQ 2Q11 | B26: 40390 | C26: 321804
A27: FQ 3Q11 | B27: 40482 | C27: 339179
A28: FQ 4Q11 | B28: 40574 | C28: 473659 | D28: =SUM(C25:C28) -> 1454838
A29: FQ 1Q12 | B29: 40663 | C29: 386006 | H29: ="ULTA Yearly Sales"&CHAR(10)&" "&TEXT(B30,"mmm yyyy")&" to "&TEXT(B112,"mmm yyyy") -> ULTA Yearly Sales Jul 2011 to Jan 1900
A30: FQ 2Q12 | B30: 40755 | C30: 394567
A31: FQ 3Q12 | B31: 40847 | C31: 413067
A32: FQ 4Q12 | B32: 40939 | C32: 582511 | D32: =SUM(C29:C32) -> 1776151
A33: FQ 1Q13 | B33: 41029 | C33: 474098
A34: FQ 2Q13 | B34: 41121 | C34: 481683
A35: FQ 3Q13 | B35: 41213 | C35: 505640
A36: FQ 4Q13 | B36: 41365 | C36: 758835 | D36: =SUM(C33:C36) -> 2220256
A37: FQ 1Q14 | B37: 41435 | C37: 582712
A38: FQ 2Q14 | B38: 41528 | C38: 600998
A39: FQ 3Q14 | B39: 41612 | C39: 618781
A40: FQ 4Q14 | B40: 41728 | C40: 868082 | D40: =SUM(C37:C40) -> 2670573
A41: FQ 1Q15 | B41: 41794 | C41: 713770
A42: FQ 2Q15 | B42: 41823 | C42: 734236
A43: FQ 3Q15 | B43: 41976 | C43: 745722
A44: FQ 4Q15 | B44: 42091 | C44: 1047641 | D44: =SUM(C41:C44) -> 3241369
A45: FQ 1Q16 | B45: 42157 | C45: 868122
A46: FQ 2Q16 | B46: 42241 | C46: 876999
A47: FQ 3Q16 | B47: 42339 | C47: 910700
A48: FQ 4Q16 | B48: 42463 | C48: 1268295 | D48: =SUM(C45:C48) -> 3924116
A49: FQ 1Q17 | B49: 42522 | C49: 1073716
A50: FQ 2Q17 | B50: 42613 | C50: 1069215
A51: FQ 3Q17 | B51: 42704 | C51: 1131232
A52: FQ 4Q17 | B52: 42827 | C52: 1580574 | D52: =SUM(C49:C52) -> 4854737
A53: FQ 1Q18 | B53: 42887 | C53: 1314879
A54: FQ 2Q18 | B54: 42977 | C54: 1289854
A55: FQ 3Q18 | B55: 43075 | C55: 1342181
A56: FQ 4Q18 | B56: 43186 | C56: 1937592 | D56: =SUM(C53:C56) -> 5884506
A57: FQ 1Q19 | B57: 43250 | C57: 1543667
A58: FQ 2Q19 | B58: 43341 | C58: 1488221
A59: FQ 3Q19 | B59: 43439 | C59: 1560011
A60: FQ 4Q19 | B60: 43550 | C60: 2124716 | D60: =SUM(C57:C60) -> 6716615
A61: FQ 1Q20 | B61: 43613 | C61: 1743029
A62: FQ 2Q20 | B62: 43704 | C62: 1666607
A63: FQ 3Q20 | B63: 43802 | C63: 1682514
A64: FQ 4Q20 | B64: 43915 | C64: 2305918 | D64: =SUM(C61:C64) -> 7398068
A65: FQ 1Q21 | B65: 43978 | C65: 1173210
A66: FQ 2Q21 | B66: 44068 | C66: 1228009
A67: FQ 3Q21 | B67: 44167 | C67: 1552033
A68: FQ 4Q21 | B68: 44279 | C68: 2198701 | D68: =SUM(C65:C68) -> 6151953
A69: FQ 1Q22 | B69: 44342 | C69: 1938519
A70: FQ 2Q22 | B70: 44433 | C70: 1967207
A71: FQ 3Q22 | B71: 44531 | C71: 1995775
A72: FQ 4Q22 | B72: 44646 | C72: 2729388 | D72: =SUM(C69:C72) -> 8630889
A73: FQ 1Q23 | B73: 44706 | C73: 2345901
A74: FQ 2Q23 | B74: 44797 | C74: 2297113
A75: FQ 3Q23 | B75: 44895 | C75: 2338793
A76: FQ 4Q23 | B76: 45012 | C76: 3226773 | D76: =SUM(C73:C76) -> 10208580
A77: FQ 1Q24 | B77: 45076 | C77: 2634263
A78: FQ 2Q24 | B78: 45167 | C78: 2529809
A79: FQ 3Q24 | B79: 45265 | C79: 2488933
A80: FQ 4Q24 | B80: 45378 | C80: 3554298 | D80: =SUM(C77:C80) -> 11207303
A81: FQ 1Q25 | B81: 45441 | C81: 2725848
A82: FQ 2Q25 | B82: 45532 | C82: 2552087
A83: FQ 3Q25 | B83: 45631 | C83: 2530100
A84: FQ 4Q25 | B84: 45743 | C84: 3487619 | D84: =SUM(C81:C84) -> 11295654
A85: FQ 1Q26 | B85: 45806 | C85: 2848367
A86: FQ 2Q26 | B86: 45897 | C86: 2788469
A87: FQ 3Q26 | B87: 45995 | C87: 2857623
A89: *All figures in thousands of dollars (USD)

Sheet ULTA %Sales & Trend
E1: Provission for Income tax
B2: Forecasting Variable Costs (% of Sales Method) & Fixed Investment or Fixed Expense (Trend Method)
B4: Date | C4: Y Sales | D4: Q Sales | E4: Income tax | F4: Other (Non-Operating) Expenses | G4: Total Operating Exp. | H4: Cost of Sales | I4: net PPE
A5: Actual | B5: ='ULTA Q Rev (Acual)'!B5 -> 38472 | D5: ='ULTA Q Rev (Acual)'!C5 -> 144769 | H5: No data found. | I5: No data found.
B6: ='ULTA Q Rev (Acual)'!B6 -> 38564 | D6: ='ULTA Q Rev (Acual)'!C6 -> 144769 | H6: No data found. | I6: No data found.
B7: ='ULTA Q Rev (Acual)'!B7 -> 38656 | D7: ='ULTA Q Rev (Acual)'!C7 -> 144769 | H7: No data found. | I7: No data found.
B8: ='ULTA Q Rev (Acual)'!B8 -> 38748 | C8: =SUM(B5:B8) -> 154440 | D8: ='ULTA Q Rev (Acual)'!C8 -> 144768 | H8: No data found. | I8: 133003
B9: ='ULTA Q Rev (Acual)'!B9 -> 38837 | D9: ='ULTA Q Rev (Acual)'!C9 -> 159468 | H9: No data found. | I9: No data found.
B10: ='ULTA Q Rev (Acual)'!B10 -> 38929 | D10: ='ULTA Q Rev (Acual)'!C10 -> 162558 | H10: No data found. | I10: No data found.
B11: ='ULTA Q Rev (Acual)'!B11 -> 39021 | D11: ='ULTA Q Rev (Acual)'!C11 -> 216544 | H11: No data found. | I11: No data found.
B12: ='ULTA Q Rev (Acual)'!B12 -> 39113 | C12: =SUM(B9:B12) -> 155900 | D12: ='ULTA Q Rev (Acual)'!C12 -> 216543 | H12: No data found. | I12: 162080
B13: ='ULTA Q Rev (Acual)'!B13 -> 39202 | D13: ='ULTA Q Rev (Acual)'!C13 -> 194113 | H13: 134600 | I13: 174916
B14: ='ULTA Q Rev (Acual)'!B14 -> 39293 | D14: ='ULTA Q Rev (Acual)'!C14 -> 200449 | H14: 141417 | I14: 196919
B15: ='ULTA Q Rev (Acual)'!B15 -> 39386 | D15: ='ULTA Q Rev (Acual)'!C15 -> 208235 | H15: 140156 | I15: 226533
B16: ='ULTA Q Rev (Acual)'!B16 -> 39478 | C16: =SUM(B13:B16) -> 157359 | D16: ='ULTA Q Rev (Acual)'!C16 -> 309344 | H16: 212322 | I16: 236389
B17: ='ULTA Q Rev (Acual)'!B17 -> 39568 | D17: ='ULTA Q Rev (Acual)'!C17 -> 239298 | H17: 165377 | I17: 255123
B18: ='ULTA Q Rev (Acual)'!B18 -> 39660 | D18: ='ULTA Q Rev (Acual)'!C18 -> 249111 | H18: 175965 | I18: 278378
B19: ='ULTA Q Rev (Acual)'!B19 -> 39752 | D19: ='ULTA Q Rev (Acual)'!C19 -> 254843 | H19: 175368 | I19: 292120
B20: ='ULTA Q Rev (Acual)'!B20 -> 39844 | C20: =SUM(B17:B20) -> 158824 | D20: ='ULTA Q Rev (Acual)'!C20 -> 341394 | H20: 240002 | I20: 292224
B21: ='ULTA Q Rev (Acual)'!B21 -> 39933 | D21: ='ULTA Q Rev (Acual)'!C21 -> 268825 | H21: 189283 | I21: 286140
B22: ='ULTA Q Rev (Acual)'!B22 -> 40025 | D22: ='ULTA Q Rev (Acual)'!C22 -> 273539 | H22: 194825 | I22: 288537
B23: ='ULTA Q Rev (Acual)'!B23 -> 40117 | D23: ='ULTA Q Rev (Acual)'!C23 -> 284043 | H23: 192372 | I23: 293746
B24: ='ULTA Q Rev (Acual)'!B24 -> 40209 | C24: =SUM(B21:B24) -> 160284 | D24: ='ULTA Q Rev (Acual)'!C24 -> 396364 | H24: 269722 | I24: 290861
B25: ='ULTA Q Rev (Acual)'!B25 -> 40298 | D25: ='ULTA Q Rev (Acual)'!C25 -> 320196 | H25: 215661 | I25: 285766
B26: ='ULTA Q Rev (Acual)'!B26 -> 40390 | D26: ='ULTA Q Rev (Acual)'!C26 -> 321804 | H26: 217846 | I26: 301333
B27: ='ULTA Q Rev (Acual)'!B27 -> 40482 | D27: ='ULTA Q Rev (Acual)'!C27 -> 339179 | H27: 220273 | I27: 331390
B28: ='ULTA Q Rev (Acual)'!B28 -> 40574 | C28: =SUM(B25:B28) -> 161744 | D28: ='ULTA Q Rev (Acual)'!C28 -> 473659 | H28: 316973 | I28: 326099
B29: ='ULTA Q Rev (Acual)'!B29 -> 40663 | D29: ='ULTA Q Rev (Acual)'!C29 -> 386006 | H29: 251101 | I29: 332147
B30: ='ULTA Q Rev (Acual)'!B30 -> 40755 | D30: ='ULTA Q Rev (Acual)'!C30 -> 394567 | H30: 260280 | I30: 351576
B31: ='ULTA Q Rev (Acual)'!B31 -> 40847 | D31: ='ULTA Q Rev (Acual)'!C31 -> 413067 | H31: 263884 | I31: 373794
B32: ='ULTA Q Rev (Acual)'!B32 -> 40939 | C32: =SUM(B29:B32) -> 163204 | D32: ='ULTA Q Rev (Acual)'!C32 -> 582511 | H32: 384046 | I32: 376985
B33: ='ULTA Q Rev (Acual)'!B33 -> 41029 | D33: ='ULTA Q Rev (Acual)'!C33 -> 474098 | H33: 303186 | I33: 384904
B34: ='ULTA Q Rev (Acual)'!B34 -> 41121 | D34: ='ULTA Q Rev (Acual)'!C34 -> 481683 | H34: 314058 | I34: 421063
B35: ='ULTA Q Rev (Acual)'!B35 -> 41213 | D35: ='ULTA Q Rev (Acual)'!C35 -> 505640 | H35: 320147 | I35: 467165
B36: ='ULTA Q Rev (Acual)'!B36 -> 41365 | C36: =SUM(B33:B36) -> 164728 | D36: ='ULTA Q Rev (Acual)'!C36 -> 758835 | H36: 499191 | I36: 483059
B37: ='ULTA Q Rev (Acual)'!B37 -> 41435 | D37: ='ULTA Q Rev (Acual)'!C37 -> 582712 | H37: 378763 | I37: 499395
B38: ='ULTA Q Rev (Acual)'!B38 -> 41528 | D38: ='ULTA Q Rev (Acual)'!C38 -> 600998 | H38: 388921 | I38: 541557
B39: ='ULTA Q Rev (Acual)'!B39 -> 41612 | D39: ='ULTA Q Rev (Acual)'!C39 -> 618781 | H39: 387120 | I39: 590132
B40: ='ULTA Q Rev (Acual)'!B40 -> 41728 | C40: =SUM(B37:B40) -> 166303 | D40: ='ULTA Q Rev (Acual)'!C40 -> 868082 | H40: 574521 | I40: 595736
B41: ='ULTA Q Rev (Acual)'!B41 -> 41794 | D41: ='ULTA Q Rev (Acual)'!C41 -> 713770 | H41: 467817 | I41: 603933
B42: ='ULTA Q Rev (Acual)'!B42 -> 41823 | D42: ='ULTA Q Rev (Acual)'!C42 -> 734236 | H42: 474894 | I42: 646890
B43: ='ULTA Q Rev (Acual)'!B43 -> 41976 | D43: ='ULTA Q Rev (Acual)'!C43 -> 745722 | H43: 463967 | I43: 686898
B44: ='ULTA Q Rev (Acual)'!B44 -> 42091 | C44: =SUM(B41:B44) -> 167684 | D44: ='ULTA Q Rev (Acual)'!C44 -> 1047641 | H44: 697904 | I44: 717159
B45: ='ULTA Q Rev (Acual)'!B45 -> 42157 | D45: ='ULTA Q Rev (Acual)'!C45 -> 868122 | E45: 40947 | F45: -2806 | G45: 192485 | H45: 564938 | I45: 744665
B46: ='ULTA Q Rev (Acual)'!B46 -> 42241 | D46: ='ULTA Q Rev (Acual)'!C46 -> 876999 | E46: 44567 | F46: -3802 | G46: 183937 | H46: 570524 | I46: 791904
B47: ='ULTA Q Rev (Acual)'!B47 -> 42339 | D47: ='ULTA Q Rev (Acual)'!C47 -> 910700 | E47: 39982 | F47: -5823 | G47: 218763 | H47: 575062 | I47: 844238
B48: ='ULTA Q Rev (Acual)'!B48 -> 42463 | C48: =SUM(B45:B48) -> 169200 | D48: ='ULTA Q Rev (Acual)'!C48 -> 1268295 | E48: 61936 | F48: -1108 | G48: 268169 | H48: 829259 | I48: 847600
B49: ='ULTA Q Rev (Acual)'!B49 -> 42522 | D49: ='ULTA Q Rev (Acual)'!C49 -> 1073716 | E49: 55503 | F49: -2227 | G49: 240724 | H49: 683286 | I49: 870835
B50: ='ULTA Q Rev (Acual)'!B50 -> 42613 | D50: ='ULTA Q Rev (Acual)'!C50 -> 1069215 | E50: 54013 | F50: -4441 | G50: 236380 | H50: 684377 | I50: 919597
B51: ='ULTA Q Rev (Acual)'!B51 -> 42704 | D51: ='ULTA Q Rev (Acual)'!C51 -> 1131232 | E51: 52310 | F51: -6717 | G51: 280464 | H51: 704179 | I51: 1001938
B52: ='ULTA Q Rev (Acual)'!B52 -> 42827 | C52: =SUM(B49:B52) -> 170666 | D52: ='ULTA Q Rev (Acual)'!C52 -> 1580574 | E52: 84128 | F52: -4296 | G52: 316266 | H52: 1035666 | I52: 1004358
B53: ='ULTA Q Rev (Acual)'!B53 -> 42887 | D53: ='ULTA Q Rev (Acual)'!C53 -> 1314879 | E53: 60520 | F53: -3820 | G53: 283445 | H53: 838871 | I53: 1020853
B54: ='ULTA Q Rev (Acual)'!B54 -> 42977 | D54: ='ULTA Q Rev (Acual)'!C54 -> 1289854 | E54: 66162 | F54: -5544 | G54: 283427 | H54: 820528 | I54: 1095135
B55: ='ULTA Q Rev (Acual)'!B55 -> 43075 | D55: ='ULTA Q Rev (Acual)'!C55 -> 1342181 | E55: 58338 | F55: -9416 | G55: 320729 | H55: 849053 | I55: 1172682
B56: ='ULTA Q Rev (Acual)'!B56 -> 43186 | C56: =SUM(B53:B56) -> 172125 | D56: ='ULTA Q Rev (Acual)'!C56 -> 1937592 | E56: 46605 | F56: -3938 | G56: 399631 | H56: 1279245 | I56: 1189453
B57: ='ULTA Q Rev (Acual)'!B57 -> 43250 | D57: ='ULTA Q Rev (Acual)'!C57 -> 1543667 | E57: 46771 | F57: -3922 | G57: 345624 | H57: 982954 | I57: 1190969
B58: ='ULTA Q Rev (Acual)'!B58 -> 43341 | D58: ='ULTA Q Rev (Acual)'!C58 -> 1488221 | E58: 46635 | F58: -3361 | G58: 337142 | H58: 952760 | I58: 1212978
B59: ='ULTA Q Rev (Acual)'!B59 -> 43439 | D59: ='ULTA Q Rev (Acual)'!C59 -> 1560011 | E59: 39365 | F59: -6294 | G59: 395453 | H59: 987733 | I59: 1257775
B60: ='ULTA Q Rev (Acual)'!B60 -> 43550 | C60: =SUM(B57:B60) -> 173580 | D60: ='ULTA Q Rev (Acual)'!C60 -> 2124716 | E60: 67811 | F60: -1129 | G60: 457245 | H60: 1383857 | I60: 1226029
B61: ='ULTA Q Rev (Acual)'!B61 -> 43613 | D61: ='ULTA Q Rev (Acual)'!C61 -> 1743029 | E61: 47365 | F61: -2128 | G61: 403133 | H61: 1098182 | I61: 2685051
B62: ='ULTA Q Rev (Acual)'!B62 -> 43704 | D62: ='ULTA Q Rev (Acual)'!C62 -> 1666607 | E62: 48431 | F62: -3367 | G62: 392843 | H62: 1060708 | I62: 2719504
B63: ='ULTA Q Rev (Acual)'!B63 -> 43802 | D63: ='ULTA Q Rev (Acual)'!C63 -> 1682514 | E63: 38933 | F63: -5555 | G63: 449198 | H63: 1059081 | I63: 2762936
B64: ='ULTA Q Rev (Acual)'!B64 -> 43915 | C64: =SUM(B61:B64) -> 175034 | D64: ='ULTA Q Rev (Acual)'!C64 -> 2305918 | E64: 65476 | F64: -3148 | G64: 515542 | H64: 1499033 | I64: 2743089
B65: ='ULTA Q Rev (Acual)'!B65 -> 43978 | D65: ='ULTA Q Rev (Acual)'!C65 -> 1173210 | E65: -24247 | F65: -25449 | G65: 380912 | H65: 869605 | I65: 2731831
B66: ='ULTA Q Rev (Acual)'!B66 -> 44068 | D66: ='ULTA Q Rev (Acual)'!C66 -> 1228009 | E66: 2086 | F66: -47282 | G66: 271587 | H66: 899002 | I66: 2626064
B67: ='ULTA Q Rev (Acual)'!B67 -> 44167 | D67: ='ULTA Q Rev (Acual)'!C67 -> 1552033 | E67: 25096 | F67: -29247 | G67: 416378 | H67: 1006514 | I67: 2552292
B68: ='ULTA Q Rev (Acual)'!B68 -> 44279 | C68: =SUM(B65:B68) -> 176492 | D68: ='ULTA Q Rev (Acual)'!C68 -> 2198701 | E68: 52315 | F68: -33079 | G68: 514140 | H68: 1427673 | I68: 2500409
B69: ='ULTA Q Rev (Acual)'!B69 -> 44342 | D69: ='ULTA Q Rev (Acual)'!C69 -> 1938519 | E69: 74677 | F69: -4947 | G69: 443875 | H69: 1184731 | I69: 2448056
B70: ='ULTA Q Rev (Acual)'!B70 -> 44433 | D70: ='ULTA Q Rev (Acual)'!C70 -> 1967207 | E70: 80989 | F70: -1782 | G70: 464299 | H70: 1169244 | I70: 2379673
B71: ='ULTA Q Rev (Acual)'!B71 -> 44531 | D71: ='ULTA Q Rev (Acual)'!C71 -> 1995775 | E71: 68537 | F71: -2245 | G71: 503403 | H71: 1206301 | I71: 2373198
B72: ='ULTA Q Rev (Acual)'!B72 -> 44646 | C72: =SUM(B69:B72) -> 177952 | D72: ='ULTA Q Rev (Acual)'!C72 -> 2729388 | E72: 85789 | F72: -2206 | G72: 649968 | H72: 1702059 | I72: 2396732
B73: ='ULTA Q Rev (Acual)'!B73 -> 44706 | D73: ='ULTA Q Rev (Acual)'!C73 -> 2345901 | E73: 105912 | F73: -2749 | G73: 500970 | H73: 1404875 | I73: 2397583
B74: ='ULTA Q Rev (Acual)'!B74 -> 44797 | D74: ='ULTA Q Rev (Acual)'!C74 -> 2297113 | E74: 95859 | F74: -2169 | G74: 534459 | H74: 1368949 | I74: 2421263
B75: ='ULTA Q Rev (Acual)'!B75 -> 44895 | D75: ='ULTA Q Rev (Acual)'!C75 -> 2338793 | E75: 88120 | F75: -2948 | G75: 597164 | H75: 1375976 | I75: 2523979
B76: ='ULTA Q Rev (Acual)'!B76 -> 45012 | C76: =SUM(B73:B76) -> 179410 | D76: ='ULTA Q Rev (Acual)'!C76 -> 3226773 | E76: 111245 | F76: 2199 | G76: 762706 | H76: 2014270 | I76: 2570536
B77: ='ULTA Q Rev (Acual)'!B77 -> 45076 | D77: ='ULTA Q Rev (Acual)'!C77 -> 2634263 | E77: 102367 | F77: 6690 | G77: 612129 | H77: 1579406 | I77: 2579538
B78: ='ULTA Q Rev (Acual)'!B78 -> 45167 | D78: ='ULTA Q Rev (Acual)'!C78 -> 2529809 | E78: 95989 | F78: 3171 | G78: 600692 | H78: 1536197 | I78: 2622290
B79: ='ULTA Q Rev (Acual)'!B79 -> 45265 | D79: ='ULTA Q Rev (Acual)'!C79 -> 2488933 | E79: 80241 | F79: -963 | G79: 661380 | H79: 1496866 | I79: 2696190
B80: ='ULTA Q Rev (Acual)'!B80 -> 45378 | C80: =SUM(B77:B80) -> 180886 | D80: ='ULTA Q Rev (Acual)'!C80 -> 3554298 | E80: 126049 | F80: 214 | G80: 820360 | H80: 2213734 | I80: 2756865
B81: ='ULTA Q Rev (Acual)'!B81 -> 45441 | D81: ='ULTA Q Rev (Acual)'!C81 -> 2725848 | E81: 94735 | F81: 3981 | G81: 665913 | H81: 1656068 | I81: 2757425
B82: ='ULTA Q Rev (Acual)'!B82 -> 45532 | D82: ='ULTA Q Rev (Acual)'!C82 -> 2552087 | E82: 81171 | F82: 371 | G82: 644821 | H82: 1573910 | I82: 2825585
B83: ='ULTA Q Rev (Acual)'!B83 -> 45631 | D83: ='ULTA Q Rev (Acual)'!C83 -> 2530100 | E83: 77997 | F83: -3209 | G83: 682259 | H83: 1524456 | I83: 2883474
B84: ='ULTA Q Rev (Acual)'!B84 -> 45743 | C84: =SUM(B81:B84) -> 182347 | D84: ='ULTA Q Rev (Acual)'!C84 -> 3487619 | E84: 125045 | F84: 262 | G84: 815599 | H84: 2153967 | I84: 2849165
B85: ='ULTA Q Rev (Acual)'!B85 -> 45806 | D85: ='ULTA Q Rev (Acual)'!C85 -> 2848367 | E85: 99644 | F85: 1718 | G85: 710613 | H85: 1734148 | I85: 2910121
B86: ='ULTA Q Rev (Acual)'!B86 -> 45897 | D86: ='ULTA Q Rev (Acual)'!C86 -> 2788469 | E86: 84795 | F86: -3692 | G86: 741737 | H86: 1696773 | I86: 3014654
B87: ='ULTA Q Rev (Acual)'!B87 -> 45995 | D87: ='ULTA Q Rev (Acual)'!C87 -> 2857623 | E87: 73436 | F87: -9449 | G87: 840920 | H87: 1701958 | I87: 3077308
A88: Forecast | B88: 46108 | C88: Q4 FY26 | E88: {=TREND(E45:E87,B45:B87,B88:B93,TRUE)} -> 98039.974 | F88: {=TREND(F45:F87,B45:B87,B88:B93,TRUE)} -> -3197.8453 | G88: {=TREND(G45:G87,B45:B87,B88:B93,TRUE)} -> 786354.46 | H88: {=TREND(H13:H87,B13:B87,B88:B93,TRUE)} -> 1781573.7 | I88: {=TREND(I13:I87,B13:B87,B88:B93,TRUE)} -> 3042601.1
B89: 46234 | C89: Q1 FY27 | E89: 99978.009 | F89: -3056.1185 | G89: 805786.25 | H89: 1815657.7 | I89: 3103816.3
B90: 46262 | C90: Q2 FY27 | E90: 100408.68 | F90: -3024.6237 | G90: 810104.42 | H90: 1823232 | I90: 3117419.6
B91: 46360 | C91: Q3 FY27 | E91: 101916.04 | F91: -2914.3917 | G91: 825218.04 | H91: 1849741.8 | I91: 3165031.4
B92: 46473 | C92: Q4 FY27 | E92: 103654.12 | F92: -2787.2876 | G92: 842644.96 | H92: 1880309.2 | I92: 3219930.7
B93: 46599 | C93: Q1 FY27 | E93: 105592.16 | F93: -2645.5608 | G93: 862076.74 | H93: 1914393.3 | I93: 3281145.8
B94: *All figures in thousands of dollars

Sheet ULTA CMA
B2: ULTA Quarter Sales Forecasting: Trend Method (Central Moving Average)
B3: : A wrong ST financial planning application for a firm if it has Seasonality
B5: Date | C5: Q Sales | D5: CMA4
A6: Actual | B6: ='ULTA Q Rev (Acual)'!B5 -> 38472 | C6: ='ULTA Q Rev (Acual)'!C5 -> 144769
B7: ='ULTA Q Rev (Acual)'!B6 -> 38564 | C7: ='ULTA Q Rev (Acual)'!C6 -> 144769
B8: ='ULTA Q Rev (Acual)'!B7 -> 38656 | C8: ='ULTA Q Rev (Acual)'!C7 -> 144769 | D8: =AVERAGE(AVERAGE(C6:C9),AVERAGE(C7:C10)) -> 146606.12
B9: ='ULTA Q Rev (Acual)'!B8 -> 38748 | C9: ='ULTA Q Rev (Acual)'!C8 -> 144768 | D9: =AVERAGE(AVERAGE(C7:C10),AVERAGE(C8:C11)) -> 150667.12
B10: ='ULTA Q Rev (Acual)'!B9 -> 38837 | C10: ='ULTA Q Rev (Acual)'!C9 -> 159468 | D10: =AVERAGE(AVERAGE(C8:C11),AVERAGE(C9:C12)) -> 161862.62
B11: ='ULTA Q Rev (Acual)'!B10 -> 38929 | C11: ='ULTA Q Rev (Acual)'!C10 -> 162558 | D11: =AVERAGE(AVERAGE(C9:C12),AVERAGE(C10:C13)) -> 179806.38
B12: ='ULTA Q Rev (Acual)'!B11 -> 39021 | C12: ='ULTA Q Rev (Acual)'!C11 -> 216544 | D12: =AVERAGE(AVERAGE(C10:C13),AVERAGE(C11:C14)) -> 193108.88
B13: ='ULTA Q Rev (Acual)'!B12 -> 39113 | C13: ='ULTA Q Rev (Acual)'!C12 -> 216543 | D13: =AVERAGE(AVERAGE(C11:C14),AVERAGE(C12:C15)) -> 202175.88
B14: ='ULTA Q Rev (Acual)'!B13 -> 39202 | C14: ='ULTA Q Rev (Acual)'!C13 -> 194113 | D14: =AVERAGE(AVERAGE(C12:C15),AVERAGE(C13:C16)) -> 205873.62
B15: ='ULTA Q Rev (Acual)'!B14 -> 39293 | C15: ='ULTA Q Rev (Acual)'!C14 -> 200449 | D15: =AVERAGE(AVERAGE(C13:C16),AVERAGE(C14:C17)) -> 216435.12
B16: ='ULTA Q Rev (Acual)'!B15 -> 39386 | C16: ='ULTA Q Rev (Acual)'!C15 -> 208235 | D16: =AVERAGE(AVERAGE(C14:C17),AVERAGE(C15:C18)) -> 233683.38
B17: ='ULTA Q Rev (Acual)'!B16 -> 39478 | C17: ='ULTA Q Rev (Acual)'!C16 -> 309344 | D17: =AVERAGE(AVERAGE(C15:C18),AVERAGE(C16:C19)) -> 245414.25
B18: ='ULTA Q Rev (Acual)'!B17 -> 39568 | C18: ='ULTA Q Rev (Acual)'!C17 -> 239298 | D18: =AVERAGE(AVERAGE(C16:C19),AVERAGE(C17:C20)) -> 257323
B19: ='ULTA Q Rev (Acual)'!B18 -> 39660 | C19: ='ULTA Q Rev (Acual)'!C18 -> 249111 | D19: =AVERAGE(AVERAGE(C17:C20),AVERAGE(C18:C21)) -> 267155.25
... B84: ='ULTA Q Rev (Acual)'!B83 -> 45631 | C84: ='ULTA Q Rev (Acual)'!C83 -> 2530100 | D84: =AVERAGE(AVERAGE(C82:C85),AVERAGE(C83:C86)) -> 2839228.4
B85: ='ULTA Q Rev (Acual)'!B84 -> 45743 | C85: ='ULTA Q Rev (Acual)'!C84 -> 3487619 | D85: =AVERAGE(AVERAGE(C83:C86),AVERAGE(C84:C88)) -> 2884479.2
B86: ='ULTA Q Rev (Acual)'!B85 -> 45806 | C86: ='ULTA Q Rev (Acual)'!C85 -> 2848367 | D86: =AVERAGE(AVERAGE(C84:C88),AVERAGE(C85:C89)) -> 2941056.4
B87: ='ULTA Q Rev (Acual)'!B86 -> 45897 | C87: ='ULTA Q Rev (Acual)'!C85 -> 2848367 | D87: =AVERAGE(AVERAGE(C84:C88),AVERAGE(C85:C89)) -> 2941056.4
B88: ='ULTA Q Rev (Acual)'!B87 -> 45995 | C88: 2857623 | D88: =AVERAGE(AVERAGE(C85:C89),AVERAGE(C86:C90)) -> 2903741.5
A89: Forecast | B89: 46108 | C89: {=TREND(C6:C88,B6:B88,B89:B94,TRUE)} -> 2796511.6 | D89: =AVERAGE(AVERAGE(C86:C90),AVERAGE(C88:C91)) -> 2840106.3
B90: 46234 | C90: 2848059.4 | D90: =AVERAGE(AVERAGE(C88:C91),AVERAGE(C89:C92)) -> 2845675.1
B91: 46262 | C91: 2859514.4 | D91: =AVERAGE(AVERAGE(C89:C92),AVERAGE(C90:C93)) -> 2869588.8
B92: 46360 | C92: 2899607.2 | D92: =AVERAGE(AVERAGE(C90:C93),AVERAGE(C91:C94)) -> 2906920
B93: 46473 | C93: 2945836.6
B94: 46599 | C94: 2997384.4
B95: *All figures in thousands of dollars

Sheet ULTA Forecast Factors
B2: ULTA Quarter Sales Components: Trend, Seasonality, & Irregularity
B3: A. Data | K3: B. Seasonal Index
B4: Date | C4: Fiscal QTR | D4: Sales | E4: Trend CMA4 | F4: Raw Seasonals | G4: Seasonal Index | H4: Irregularity Index | I4: Sales Reconstruction | K4: Quarter | L4: Raw Factors | M4: Normalized Seaonal Index
B5: ='ULTA Q Rev (Acual)'!B5 -> 38472 | C5: 1 | D5: ='ULTA Q Rev (Acual)'!C5 -> 144769 | K5: 1 | L5: =AVERAGEIF($C$7:$C$87,K5,$F$7:$F$87) -> 0.94814945 | M5: =L5/AVERAGE($L$5:$L$8) -> 0.94732421
B6: ='ULTA Q Rev (Acual)'!B6 -> 38564 | C6: 2 | D6: ='ULTA Q Rev (Acual)'!C6 -> 144769 | K6: 2 | L6: =AVERAGEIF($C$7:$C$87,K6,$F$7:$F$87) -> 0.91163847 | M6: =L6/AVERAGE($L$5:$L$8) -> 0.91084501
B7: ='ULTA Q Rev (Acual)'!B7 -> 38656 | C7: 3 | D7: ='ULTA Q Rev (Acual)'!C7 -> 144769 | E7: =AVERAGE(AVERAGE(D5:D8),AVERAGE(D6:D9)) -> 146606.12 | F7: =D7/E7 -> 0.98746898 | G7: =VLOOKUP(C7,$K$5:$M$8,3) -> 0.93270981 | H7: =D7/(E7*G7) -> 1.0587098 | I7: =E7*G7*H7 -> 144769 | K7: 3 | L7: =AVERAGEIF($C$7:$C$87,K7,$F$7:$F$87) -> 0.93352232 | M7: =L7/AVERAGE($L$5:$L$8) -> 0.93270981
B8: ='ULTA Q Rev (Acual)'!B8 -> 38748 | C8: 4 | D8: ='ULTA Q Rev (Acual)'!C8 -> 144768 | E8: =AVERAGE(AVERAGE(D6:D9),AVERAGE(D7:D10)) -> 150667.12 | F8: =D8/E8 -> 0.96084663 | G8: =VLOOKUP(C8,$K$5:$M$8,3) -> 1.209121 | H8: =D8/(E8*G8) -> 0.79466543 | I8: =E8*G8*H8 -> 144768 | K8: 4 | L8: =AVERAGEIF($C$7:$C$87,K8,$F$7:$F$87) -> 1.2101743 | M8: =L8/AVERAGE($L$5:$L$8) -> 1.209121
B9: ='ULTA Q Rev (Acual)'!B9 -> 38837 | C9: 1 | D9: ='ULTA Q Rev (Acual)'!C9 -> 159468 | E9: =AVERAGE(AVERAGE(D7:D10),AVERAGE(D8:D11)) -> 161862.62 | F9: =D9/E9 -> 0.98520582 | G9: =VLOOKUP(C9,$K$5:$M$8,3) -> 0.94732421 | H9: =D9/(E9*G9) -> 1.039988 | I9: =E9*G9*H9 -> 159468
B10: ='ULTA Q Rev (Acual)'!B10 -> 38929 | C10: 2 | D10: ='ULTA Q Rev (Acual)'!C10 -> 162558 | E10: =AVERAGE(AVERAGE(D8:D11),AVERAGE(D9:D12)) -> 179806.38 | F10: =D10/E10 -> 0.90407251 | G10: =VLOOKUP(C10,$K$5:$M$8,3) -> 0.91084501 | H10: =D10/(E10*G10) -> 0.99256459 | I10: =E10*G10*H10 -> 162558
B11: ='ULTA Q Rev (Acual)'!B11 -> 39021 | C11: 3 | D11: ='ULTA Q Rev (Acual)'!C11 -> 216544 | E11: =AVERAGE(AVERAGE(D9:D12),AVERAGE(D10:D13)) -> 193108.88 | F11: =D11/E11 -> 1.1213571 | G11: =VLOOKUP(C11,$K$5:$M$8,3) -> 0.93270981 | H11: =D11/(E11*G11) -> 1.2022572 | I11: =E11*G11*H11 -> 216544
B12: ='ULTA Q Rev (Acual)'!B12 -> 39113 | C12: 4 | D12: ='ULTA Q Rev (Acual)'!C12 -> 216543 | E12: =AVERAGE(AVERAGE(D10:D13),AVERAGE(D11:D14)) -> 202175.88 | F12: =D12/E12 -> 1.0710625 | G12: =VLOOKUP(C12,$K$5:$M$8,3) -> 1.209121 | H12: =D12/(E12*G12) -> 0.88581915 | I12: =E12*G12*H12 -> 216543
B13: ='ULTA Q Rev (Acual)'!B13 -> 39202 | C13: 1 | D13: ='ULTA Q Rev (Acual)'!C13 -> 194113 | E13: =AVERAGE(AVERAGE(D11:D14),AVERAGE(D12:D15)) -> 205873.62 | F13: =D13/E13 -> 0.94287454 | G13: =VLOOKUP(C13,$K$5:$M$8,3) -> 0.94732421 | H13: =D13/(E13*G13) -> 0.9953029 | I13: =E13*G13*H13 -> 194113
B14: ='ULTA Q Rev (Acual)'!B14 -> 39293 | C14: 2 | D14: ='ULTA Q Rev (Acual)'!C14 -> 200449 | E14: =AVERAGE(AVERAGE(D12:D15),AVERAGE(D13:D16)) -> 216435.12 | F14: =D14/E14 -> 0.92613895 | G14: =VLOOKUP(C14,$K$5:$M$8,3) -> 0.91084501 | H14: =D14/(E14*G14) -> 1.0167909 | I14: =E14*G14*H14 -> 200449
B15: ='ULTA Q Rev (Acual)'!B15 -> 39386 | C15: 3 | D15: ='ULTA Q Rev (Acual)'!C15 -> 208235 | E15: =AVERAGE(AVERAGE(D13:D16),AVERAGE(D14:D17)) -> 233683.38 | F15: =D15/E15 -> 0.89109891 | G15: =VLOOKUP(C15,$K$5:$M$8,3) -> 0.93270981 | H15: =D15/(E15*G15) -> 0.95538708 | I15: =E15*G15*H15 -> 208235
B16: ='ULTA Q Rev (Acual)'!B16 -> 39478 | C16: 4 | D16: ='ULTA Q Rev (Acual)'!C16 -> 309344 | E16: =AVERAGE(AVERAGE(D14:D17),AVERAGE(D15:D18)) -> 245414.25 | F16: =D16/E16 -> 1.2604973 | G16: =VLOOKUP(C16,$K$5:$M$8,3) -> 1.209121 | H16: =D16/(E16*G16) -> 1.0424907 | I16: =E16*G16*H16 -> 309344
B17: ='ULTA Q Rev (Acual)'!B17 -> 39568 | C17: 1 | D17: ='ULTA Q Rev (Acual)'!C17 -> 239298 | E17: =AVERAGE(AVERAGE(D15:D18),AVERAGE(D16:D19)) -> 257323 | F17: =D17/E17 -> 0.92995185 | G17: =VLOOKUP(C17,$K$5:$M$8,3) -> 0.94732421 | H17: =D17/(E17*G17) -> 0.98166165 | I17: =E17*G17*H17 -> 239298
B18: ='ULTA Q Rev (Acual)'!B18 -> 39660 | C18: 2 | D18: ='ULTA Q Rev (Acual)'!C18 -> 249111 | E18: =AVERAGE(AVERAGE(D16:D19),AVERAGE(D17:D20)) -> 267155.25 | F18: =D18/E18 -> 0.93245781 | G18: =VLOOKUP(C18,$K$5:$M$8,3) -> 0.91084501 | H18: =D18/(E18*G18) -> 1.0237283 | I18: =E18*G18*H18 -> 249111
B19: ='ULTA Q Rev (Acual)'!B19 -> 39752 | C19: 3 | D19: ='ULTA Q Rev (Acual)'!C19 -> 254843 | E19: =AVERAGE(AVERAGE(D17:D20),AVERAGE(D18:D21)) -> 274852.38 | F19: =D19/E19 -> 0.92719956 | G19: =VLOOKUP(C19,$K$5:$M$8,3) -> 0.93270981 | H19: =D19/(E19*G19) -> 0.99409221 | I19: =E19*G19*H19 -> 254843
B20: ='ULTA Q Rev (Acual)'!B20 -> 39844 | C20: 4 | D20: ='ULTA Q Rev (Acual)'!C20 -> 341394 | E20: =AVERAGE(AVERAGE(D18:D21),AVERAGE(D19:D22)) -> 281596.75 | F20: =D20/E20 -> 1.2123506 | G20: =VLOOKUP(C20,$K$5:$M$8,3) -> 1.209121 | H20: =D20/(E20*G20) -> 1.0026711 | I20: =E20*G20*H20 -> 341394
... B83: ='ULTA Q Rev (Acual)'!B83 -> 45631 | C83: 3.2007722 | D83: ='ULTA Q Rev (Acual)'!C83 -> 2530100 | E83: =AVERAGE(AVERAGE(D81:D84),AVERAGE(D82:D85)) -> 2839228.4 | F83: =D83/E83 -> 0.8911224 | G83: =VLOOKUP(C83,$K$5:$M$8,3) -> 0.93270981 | H83: =D83/(E83*G83) -> 0.95541227 | I83: =E83*G83*H83 -> 2530100
B84: ='ULTA Q Rev (Acual)'!B84 -> 45743 | C84: 4 | D84: ='ULTA Q Rev (Acual)'!C84 -> 3487619 | E84: =AVERAGE(AVERAGE(D82:D85),AVERAGE(D83:D87)) -> 2878489.4 | F84: =D84/E84 -> 1.2116143 | G84: =VLOOKUP(C84,$K$5:$M$8,3) -> 1.209121 | H84: =D84/(E84*G84) -> 1.0020621 | I84: =E84*G84*H84 -> 3487619
B85: ='ULTA Q Rev (Acual)'!B85 -> 45806 | C85: 1 | D85: ='ULTA Q Rev (Acual)'!C85 -> 2848367 | E85: =AVERAGE(AVERAGE(D83:D86),AVERAGE(D84:D88)) -> 2954579.1 | F85: =D85/E85 -> 0.96405169 | G85: =VLOOKUP(C85,$K$5:$M$8,3) -> 0.94732421 | H85: =D85/(E85*G85) -> 1.0176576 | I85: =E85*G85*H85 -> 2848367
B86: ='ULTA Q Rev (Acual)'!B86 -> 45897 | C86: 2 | D86: ='ULTA Q Rev (Acual)'!C86 -> 2788469 | E86: =AVERAGE(AVERAGE(D84:D87),AVERAGE(D85:D89)) -> 2913502.9 | F86: =D86/E86 -> 0.95708468 | G86: =VLOOKUP(C86,$K$5:$M$8,3) -> 0.91084501 | H86: =D86/(E86*G86) -> 1.0507657 | I86: =E86*G86*H86 -> 2788469
B87: ='ULTA Q Rev (Acual)'!B87 -> 45995 | C87: 3 | D87: ='ULTA Q Rev (Acual)'!C87 -> 2857623 | E87: =AVERAGE(AVERAGE(D85:D88),AVERAGE(D86:D90)) -> 2827266.2 | F87: =D87/E87 -> 1.0107372 | G87: =VLOOKUP(C87,$K$5:$M$8,3) -> 0.93270981 | H87: =D87/(E87*G87) -> 1.0836566 | I87: =E87*G87*H87 -> 2857623
B88: *All figures in thousands of dollars

Sheet ULTA Expo Smooth
B2: ULTA Q Sales Forecasting: Exponential Smoothing Method
B4: Date | C4: Sales | D4: Exp Smoothing | F4: Sensitivity Factors & Forecast Error
A5: Actual | B5: ='ULTA Q Rev (Acual)'!B5 -> 38472 | C5: ='ULTA Q Rev (Acual)'!C5 -> 144769 | D5: =C5 -> 144769 | F5: Alpha | G5: 0.39536802
B6: ='ULTA Q Rev (Acual)'!B6 -> 38564 | C6: ='ULTA Q Rev (Acual)'!C6 -> 144769 | D6: =D5+$G$5*(C5-D5) -> 144769 | F6: Mean Squared Error (MSE) | G6: =SUMXMY2(C5:C87,D5:D87)/COUNT(D5:D87) -> 7.930271e+10
B7: ='ULTA Q Rev (Acual)'!B7 -> 38656 | C7: ='ULTA Q Rev (Acual)'!C7 -> 144769 | D7: =D6+$G$5*(C6-D6) -> 144769 | F7: Mean Absolute % Error (MAPE) | G7: {=AVERAGE(ABS(C5:C87-D5:D87)/C5:C87)} -> 0.10737155
B8: ='ULTA Q Rev (Acual)'!B8 -> 38748 | C8: ='ULTA Q Rev (Acual)'!C8 -> 144768 | D8: =D7+$G$5*(C7-D7) -> 144769
B9: ='ULTA Q Rev (Acual)'!B9 -> 38837 | C9: ='ULTA Q Rev (Acual)'!C9 -> 159468 | D9: =D8+$G$5*(C8-D8) -> 144768.6
B10: ='ULTA Q Rev (Acual)'!B10 -> 38929 | C10: ='ULTA Q Rev (Acual)'!C10 -> 162558 | D10: =D9+$G$5*(C9-D9) -> 150580.28
B11: ='ULTA Q Rev (Acual)'!B11 -> 39021 | C11: ='ULTA Q Rev (Acual)'!C11 -> 216544 | D11: =D10+$G$5*(C10-D10) -> 155315.88
B12: ='ULTA Q Rev (Acual)'!B12 -> 39113 | C12: ='ULTA Q Rev (Acual)'!C12 -> 216543 | D12: =D11+$G$5*(C11-D11) -> 179523.52
B13: ='ULTA Q Rev (Acual)'!B13 -> 39202 | C13: ='ULTA Q Rev (Acual)'!C13 -> 194113 | D13: =D12+$G$5*(C12-D12) -> 194159.84
B14: ='ULTA Q Rev (Acual)'!B14 -> 39293 | C14: ='ULTA Q Rev (Acual)'!C14 -> 200449 | D14: =D13+$G$5*(C13-D13) -> 194141.32
B15: ='ULTA Q Rev (Acual)'!B15 -> 39386 | C15: ='ULTA Q Rev (Acual)'!C15 -> 208235 | D15: =D14+$G$5*(C14-D14) -> 196635.18
B16: ='ULTA Q Rev (Acual)'!B16 -> 39478 | C16: ='ULTA Q Rev (Acual)'!C16 -> 309344 | D16: =D15+$G$5*(C15-D15) -> 201221.38
B17: ='ULTA Q Rev (Acual)'!B17 -> 39568 | C17: ='ULTA Q Rev (Acual)'!C17 -> 239298 | D17: =D16+$G$5*(C16-D16) -> 243969.6
B18: ='ULTA Q Rev (Acual)'!B18 -> 39660 | C18: ='ULTA Q Rev (Acual)'!C18 -> 249111 | D18: =D17+$G$5*(C17-D17) -> 242122.6
B19: ='ULTA Q Rev (Acual)'!B19 -> 39752 | C19: ='ULTA Q Rev (Acual)'!C19 -> 254843 | D19: =D18+$G$5*(C18-D18) -> 244885.59
... B87: ='ULTA Q Rev (Acual)'!B87 -> 45995 | C87: ='ULTA Q Rev (Acual)'!C87 -> 2857623 | D87: =D86+$G$5*(C86-D86) -> 2874822.8
A88: Forecast | B88: 46108 | D88: =D87+$G$5*(C87-D87) -> 2868022.6
B89: *All figures in thousands of dollars

Sheet ULTA HLTES
B2: ULTA Q Sales Forecasting: Holt's Linear Trend Exponential Smoothing Method
B4: Sensitivity Factors & Forecast Error
B5: Alpha | D5: 0.30872116
B6: Beta | D6: 0.045104274
B7: Mean Squared Error (MSE) | D7: =SUMXMY2(C13:C94,F13:F94)/COUNT(C13:C94) -> 7.1741476e+10
B8: Mean Absolute % Error (MAPE) | D8: {=AVERAGE(ABS(C13:C94-F13:F94)/C13:C94)} -> 0.10643902
B10: Sales Forecasting
B11: Date | C11: Sales | D11: Weighted Sales Level | E11: Trend | F11: Forecast
A12: Actual | B12: ='ULTA Q Rev (Acual)'!B5 -> 38472 | C12: ='ULTA Q Rev (Acual)'!C5 -> 144769 | D12: =C12 -> 144769
B13: ='ULTA Q Rev (Acual)'!B6 -> 38564 | C13: ='ULTA Q Rev (Acual)'!C6 -> 144769 | D13: =$D$5*C13+(1-$D$5)*(D12+E12) -> 144769 | E13: =$D$6*(D13-D12)+(1-$D$6)*E12 -> 0 | F13: =SUM(D12:E12) -> 144769
B14: ='ULTA Q Rev (Acual)'!B7 -> 38656 | C14: ='ULTA Q Rev (Acual)'!C7 -> 144769 | D14: =$D$5*C14+(1-$D$5)*(D13+E13) -> 144769 | E14: =$D$6*(D14-D13)+(1-$D$6)*E13 -> 0 | F14: =SUM(D13:E13) -> 144769
B15: ='ULTA Q Rev (Acual)'!B8 -> 38748 | C15: ='ULTA Q Rev (Acual)'!C8 -> 144768 | D15: =$D$5*C15+(1-$D$5)*(D14+E14) -> 144768.69 | E15: =$D$6*(D15-D14)+(1-$D$6)*E14 -> -0.013924644 | F15: =SUM(D14:E14) -> 144769
B16: ='ULTA Q Rev (Acual)'!B9 -> 38837 | C16: ='ULTA Q Rev (Acual)'!C9 -> 159468 | D16: =$D$5*C16+(1-$D$5)*(D15+E15) -> 149306.67 | E16: =$D$6*(D16-D15)+(1-$D$6)*E15 -> 204.66891 | F16: =SUM(D15:E15) -> 144768.68
B17: ='ULTA Q Rev (Acual)'!B10 -> 38929 | C17: ='ULTA Q Rev (Acual)'!C10 -> 162558 | D17: =$D$5*C17+(1-$D$5)*(D16+E16) -> 153539.12 | E17: =$D$6*(D17-D16)+(1-$D$6)*E16 -> 386.33903 | F17: =SUM(D16:E16) -> 149511.34
B18: ='ULTA Q Rev (Acual)'!B11 -> 39021 | C18: ='ULTA Q Rev (Acual)'!C11 -> 216544 | D18: =$D$5*C18+(1-$D$5)*(D17+E17) -> 173257.13 | E18: =$D$6*(D18-D17)+(1-$D$6)*E17 -> 1258.2799 | F18: =SUM(D17:E17) -> 153925.46
B19: ='ULTA Q Rev (Acual)'!B12 -> 39113 | C19: ='ULTA Q Rev (Acual)'!C12 -> 216543 | D19: =$D$5*C19+(1-$D$5)*(D18+E18) -> 187490.21 | E19: =$D$6*(D19-D18)+(1-$D$6)*E18 -> 1843.4992 | F19: =SUM(D18:E18) -> 174515.41
B20: ='ULTA Q Rev (Acual)'!B13 -> 39202 | C20: ='ULTA Q Rev (Acual)'!C13 -> 194113 | D20: =$D$5*C20+(1-$D$5)*(D19+E19) -> 190809.18 | E20: =$D$6*(D20-D19)+(1-$D$6)*E19 -> 1910.0491 | F20: =SUM(D19:E19) -> 189333.71
B21: ='ULTA Q Rev (Acual)'!B14 -> 39293 | C21: ='ULTA Q Rev (Acual)'!C14 -> 200449 | D21: =$D$5*C21+(1-$D$5)*(D20+E20) -> 195105.57 | E21: =$D$6*(D21-D20)+(1-$D$6)*E20 -> 2017.6834 | F21: =SUM(D20:E20) -> 192719.23
B22: ='ULTA Q Rev (Acual)'!B15 -> 39386 | C22: ='ULTA Q Rev (Acual)'!C15 -> 208235 | D22: =$D$5*C22+(1-$D$5)*(D21+E21) -> 200553.69 | E22: =$D$6*(D22-D21)+(1-$D$6)*E21 -> 2172.4104 | F22: =SUM(D21:E21) -> 197123.26
B23: ='ULTA Q Rev (Acual)'!B16 -> 39478 | C23: ='ULTA Q Rev (Acual)'!C16 -> 309344 | D23: =$D$5*C23+(1-$D$5)*(D22+E22) -> 235641.3 | E23: =$D$6*(D23-D22)+(1-$D$6)*E22 -> 3657.0268 | F23: =SUM(D22:E22) -> 202726.1
B24: ='ULTA Q Rev (Acual)'!B17 -> 39568 | C24: ='ULTA Q Rev (Acual)'!C17 -> 239298 | D24: =$D$5*C24+(1-$D$5)*(D23+E23) -> 239298.23 | E24: =$D$6*(D24-D23)+(1-$D$6)*E23 -> 3657.0222 | F24: =SUM(D23:E23) -> 239298.33
... B94: ='ULTA Q Rev (Acual)'!B87 -> 45995 | C94: ='ULTA Q Rev (Acual)'!C87 -> 2857623 | D94: =$D$5*C94+(1-$D$5)*(D93+E93) -> 2973225 | E94: =$D$6*(D94-D93)+(1-$D$6)*E93 -> 43808.97 | F94: =SUM(D93:E93) -> 3024852.2
A95: Forecast | B95: 46108 | F95: =$D$94+$E$94*(ROW()-ROW($F$94)) -> 3017034
B96: 46234 | F96: =$D$94+$E$94*(ROW()-ROW($F$94)) -> 3060843
B97: 46262 | F97: =$D$94+$E$94*(ROW()-ROW($F$94)) -> 3104651.9
B98: 46360 | F98: =$D$94+$E$94*(ROW()-ROW($F$94)) -> 3148460.9
B99: 46473 | F99: =$D$94+$E$94*(ROW()-ROW($F$94)) -> 3192269.9
B100: 46599 | F100: =$D$94+$E$94*(ROW()-ROW($F$94)) -> 3236078.9
B101: *All figures in thousands of dollars

Sheet ULTA HWAS
B2: ULTA Q Sales Forecasting: Holt-Winters Additive Seasonal (HWAS) Model
B4: Sensitivity Factors & Forecast Error
B5: Alpha | D5: 0.60592182
B6: Beta | D6: 0.050720547
B7: Gamma | D7: 1
B8: Mean Squared Error (MSE) | D8: =SUMXMY2(C17:C95,G17:G95)/COUNT(C17:C95) -> 1.7237242e+10
B9: Mean Absolute % Error (MAPE) | D9: {=AVERAGE(ABS(C17:C95-G17:G95)/C17:C95)} -> 0.06417144
B11: Sales Forecasting
B12: Date | C12: Sales | D12: Weighted Sales Level | E12: Trend | F12: Seasonal | G12: Forecast
A13: Actual | B13: ='ULTA Q Rev (Acual)'!B5 -> 38472 | C13: ='ULTA Q Rev (Acual)'!C5 -> 144769 | F13: =C13-$D$16 -> 0.25
B14: ='ULTA Q Rev (Acual)'!B6 -> 38564 | C14: ='ULTA Q Rev (Acual)'!C6 -> 144769 | F14: =C14-$D$16 -> 0.25
B15: ='ULTA Q Rev (Acual)'!B7 -> 38656 | C15: ='ULTA Q Rev (Acual)'!C7 -> 144769 | F15: =C15-$D$16 -> 0.25
B16: ='ULTA Q Rev (Acual)'!B8 -> 38748 | C16: ='ULTA Q Rev (Acual)'!C8 -> 144768 | D16: =AVERAGE(C13:C16) -> 144768.75 | F16: =C16-$D$16 -> -0.75
B17: ='ULTA Q Rev (Acual)'!B9 -> 38837 | C17: ='ULTA Q Rev (Acual)'!C9 -> 159468 | D17: =$D$5*(C17-F13)+(1-$D$5)*(D16+E16) -> 153675.19 | E17: =$D$6*(D17-D16)+(1-$D$6)*E16 -> 451.73975 | F17: =$D$7*(C17-D17)+(1-$D$7)*F13 -> 5792.8052 | G17: =D16+E16+F13 -> 144769
B18: ='ULTA Q Rev (Acual)'!B10 -> 38929 | C18: ='ULTA Q Rev (Acual)'!C10 -> 162558 | D18: =$D$5*(C18-F14)+(1-$D$5)*(D17+E17) -> 159235.35 | E18: =$D$6*(D18-D17)+(1-$D$6)*E17 -> 710.84135 | F18: =$D$7*(C18-D18)+(1-$D$7)*F14 -> 3322.6504 | G18: =D17+E17+F14 -> 154127.18
B19: ='ULTA Q Rev (Acual)'!B11 -> 39021 | C19: ='ULTA Q Rev (Acual)'!C11 -> 216544 | D19: =$D$5*(C19-F15)+(1-$D$5)*(D18+E18) -> 194239.89 | E19: =$D$6*(D19-D18)+(1-$D$6)*E18 -> 2450.2364 | F19: =$D$7*(C19-D19)+(1-$D$7)*F15 -> 22304.113 | G19: =D18+E18+F15 -> 159946.44
B20: ='ULTA Q Rev (Acual)'!B12 -> 39113 | C20: ='ULTA Q Rev (Acual)'!C12 -> 216543 | D20: =$D$5*(C20-F16)+(1-$D$5)*(D19+E19) -> 208719.87 | E20: =$D$6*(D20-D19)+(1-$D$6)*E19 -> 3060.3916 | F20: =$D$7*(C20-D20)+(1-$D$7)*F16 -> 7823.1311 | G20: =D19+E19+F16 -> 196689.37
B21: ='ULTA Q Rev (Acual)'!B13 -> 39202 | C21: ='ULTA Q Rev (Acual)'!C13 -> 194113 | D21: =$D$5*(C21-F17)+(1-$D$5)*(D20+E20) -> 197565.29 | E21: =$D$6*(D21-D20)+(1-$D$6)*E20 -> 2339.4008 | F21: =$D$7*(C21-D21)+(1-$D$7)*F17 -> -3452.2948 | G21: =D20+E20+F17 -> 217573.07
B22: ='ULTA Q Rev (Acual)'!B14 -> 39293 | C22: ='ULTA Q Rev (Acual)'!C14 -> 200449 | D22: =$D$5*(C22-F18)+(1-$D$5)*(D21+E21) -> 198221.24 | E22: =$D$6*(D22-D21)+(1-$D$6)*E21 -> 2254.0148 | F22: =$D$7*(C22-D22)+(1-$D$7)*F18 -> 2227.7648 | G22: =D21+E21+F18 -> 203227.35
B23: ='ULTA Q Rev (Acual)'!B15 -> 39386 | C23: ='ULTA Q Rev (Acual)'!C15 -> 208235 | D23: =$D$5*(C23-F19)+(1-$D$5)*(D22+E22) -> 191662.5 | E23: =$D$6*(D23-D22)+(1-$D$6)*E22 -> 1807.0274 | F23: =$D$7*(C23-D23)+(1-$D$7)*F19 -> 16572.497 | G23: =D22+E22+F19 -> 222779.36
B24: ='ULTA Q Rev (Acual)'!B16 -> 39478 | C24: ='ULTA Q Rev (Acual)'!C16 -> 309344 | D24: =$D$5*(C24-F20)+(1-$D$5)*(D23+E23) -> 258940.19 | E24: =$D$6*(D24-D23)+(1-$D$6)*E23 -> 5127.7353 | F24: =$D$7*(C24-D24)+(1-$D$7)*F20 -> 50403.806 | G24: =D23+E23+F20 -> 201292.66
B25: ='ULTA Q Rev (Acual)'!B17 -> 39568 | C25: ='ULTA Q Rev (Acual)'!C17 -> 239298 | D25: =$D$5*(C25-F21)+(1-$D$5)*(D24+E24) -> 251151.11 | E25: =$D$6*(D25-D24)+(1-$D$6)*E24 -> 4472.5871 | F25: =$D$7*(C25-D25)+(1-$D$7)*F21 -> -11853.109 | G25: =D24+E24+F21 -> 260615.63
B26: ='ULTA Q Rev (Acual)'!B18 -> 39660 | C26: ='ULTA Q Rev (Acual)'!C18 -> 249111 | D26: =$D$5*(C26-F22)+(1-$D$5)*(D25+E25) -> 250327.66 | E26: =$D$6*(D26-D25)+(1-$D$6)*E25 -> 4203.9693 | F26: =$D$7*(C26-D26)+(1-$D$7)*F22 -> -1216.6603 | G26: =D25+E25+F22 -> 257851.46
B27: ='ULTA Q Rev (Acual)'!B19 -> 39752 | C27: ='ULTA Q Rev (Acual)'!C19 -> 254843 | D27: =$D$5*(C27-F23)+(1-$D$5)*(D26+E26) -> 244678.66 | E27: =$D$6*(D27-D26)+(1-$D$6)*E26 -> 3704.2212 | F27: =$D$7*(C27-D27)+(1-$D$7)*F23 -> 10164.342 | G27: =D26+E26+F23 -> 271104.13
B28: ='ULTA Q Rev (Acual)'!B20 -> 39844 | C28: ='ULTA Q Rev (Acual)'!C20 -> 341394 | D28: =$D$5*(C28-F24)+(1-$D$5)*(D27+E27) -> 274199.58 | E28: =$D$6*(D28-D27)+(1-$D$6)*E27 -> 5013.6584 | F28: =$D$7*(C28-D28)+(1-$D$7)*F24 -> 67194.419 | G28: =D27+E27+F24 -> 298786.69
... B95: ='ULTA Q Rev (Acual)'!B87 -> 45995 | C95: ='ULTA Q Rev (Acual)'!C87 -> 2857623 | D95: =$D$5*(C95-F91)+(1-$D$5)*(D94+E94) -> 2965953.4 | E95: =$D$6*(D95-D94)+(1-$D$6)*E94 -> 49161.117 | F95: =$D$7*(C95-D95)+(1-$D$7)*F91 -> -108330.45 | G95: =D94+E94+F91 -> 2811977.6
A96: Forecast | B96: 46108 | G96: =$D$95+$E$95*(ROW()-ROW($G$95))+F89 -> 3019903.2
B97: 46234 | G97: =$D$95+$E$95*(ROW()-ROW($G$95))+F90 -> 2933759.5
B98: 46262 | G98: =$D$95+$E$95*(ROW()-ROW($G$95))+F91 -> 2987118.5
B99: 46360 | G99: =$D$95+$E$95*(ROW()-ROW($G$95))+F92 -> 3956269.4
B100: 46473 | G100: =$D$95+$E$95*(ROW()-ROW($G$95))+F93 -> 3258868.3
B101: 46599 | G101: =$D$95+$E$95*(ROW()-ROW($G$95))+F95 -> 3152589.7
B102: *All figures in thousands of dollars

Sheet ULTA HWMS
B2: ULTA Q Sales Forecasting: Holt-Winters Multiplicative Seasonal (HWMS) Model
B4: Sensitivity Factors & Forecast Error
B5: Alpha | E5: 0.73164851
B6: Beta | E6: 0.045839001
B7: Gamma | E7: 0.70193895
B8: Mean Squared Error (MSE) | E8: =SUMXMY2(C17:C95,G17:G95)/COUNT(C17:C95) -> 1.4107158e+10
B9: Mean Absolute % Error (MAPE) | E9: {=AVERAGE(ABS(C17:C95-G17:G95)/C17:C95)} -> 0.065372198
B11: Sales Forecasting
B12: Date | C12: Sales | D12: Level | E12: Trend | F12: Seasonal | G12: Forecast
A13: Actual | B13: ='ULTA Q Rev (Acual)'!B5 -> 38472 | C13: ='ULTA Q Rev (Acual)'!C5 -> 144769 | F13: =C13/$D$16 -> 1.0000017
B14: ='ULTA Q Rev (Acual)'!B6 -> 38564 | C14: ='ULTA Q Rev (Acual)'!C6 -> 144769 | F14: =C14/$D$16 -> 1.0000017
B15: ='ULTA Q Rev (Acual)'!B7 -> 38656 | C15: ='ULTA Q Rev (Acual)'!C7 -> 144769 | F15: =C15/$D$16 -> 1.0000017
B16: ='ULTA Q Rev (Acual)'!B8 -> 38748 | C16: ='ULTA Q Rev (Acual)'!C8 -> 144768 | D16: =AVERAGE(C13:C16) -> 144768.75 | E16: 0 | F16: =C16/$D$16 -> 0.99999482
B17: ='ULTA Q Rev (Acual)'!B9 -> 38837 | C17: ='ULTA Q Rev (Acual)'!C9 -> 159468 | D17: =$E$5*(C17/F13)+(1-$E$5)*(D16+E16) -> 155523.23 | E17: =$E$6*(D17-D16)+(1-$E$6)*E16 -> 492.97475 | F17: =$E$7*(C17/D17)+(1-$E$7)*F13 -> 1.0178048 | G17: =SUM(D16:E16)*F13 -> 144769
B18: ='ULTA Q Rev (Acual)'!B10 -> 38929 | C18: ='ULTA Q Rev (Acual)'!C10 -> 162558 | D18: =$E$5*(C18/F14)+(1-$E$5)*(D17+E17) -> 160802.29 | E18: =$E$6*(D18-D17)+(1-$E$6)*E17 -> 712.36421 | F18: =$E$7*(C18/D18)+(1-$E$7)*F14 -> 1.0076646 | G18: =SUM(D17:E17)*F14 -> 156016.48
B19: ='ULTA Q Rev (Acual)'!B11 -> 39021 | C19: ='ULTA Q Rev (Acual)'!C11 -> 216544 | D19: =$E$5*(C19/F15)+(1-$E$5)*(D18+E18) -> 201776.52 | E19: =$E$6*(D19-D18)+(1-$E$6)*E18 -> 2557.9277 | F19: =$E$7*(C19/D19)+(1-$E$7)*F15 -> 1.0513735 | G19: =SUM(D18:E18)*F15 -> 161514.94
B20: ='ULTA Q Rev (Acual)'!B12 -> 39113 | C20: ='ULTA Q Rev (Acual)'!C12 -> 216543 | D20: =$E$5*(C20/F16)+(1-$E$5)*(D19+E19) -> 213267.64 | E20: =$E$6*(D20-D19)+(1-$E$6)*E19 -> 2967.4162 | F20: =$E$7*(C20/D20)+(1-$E$7)*F16 -> 1.0107788 | G20: =SUM(D19:E19)*F16 -> 204333.39
B21: ='ULTA Q Rev (Acual)'!B13 -> 39202 | C21: ='ULTA Q Rev (Acual)'!C13 -> 194113 | D21: =$E$5*(C21/F17)+(1-$E$5)*(D20+E20) -> 197565.03 | E21: =$E$6*(D21-D20)+(1-$E$6)*E20 -> 2111.6012 | F21: =$E$7*(C21/D21)+(1-$E$7)*F17 -> 0.99304202 | G21: =SUM(D20:E20)*F17 -> 220085.08
B22: ='ULTA Q Rev (Acual)'!B14 -> 39293 | C22: ='ULTA Q Rev (Acual)'!C14 -> 200449 | D22: =$E$5*(C22/F18)+(1-$E$5)*(D21+E21) -> 199126.21 | E22: =$E$6*(D22-D21)+(1-$E$6)*E21 -> 2086.3703 | F22: =$E$7*(C22/D22)+(1-$E$7)*F18 -> 1.0069475 | G22: =SUM(D21:E21)*F18 -> 201207.07
B23: ='ULTA Q Rev (Acual)'!B15 -> 39386 | C23: ='ULTA Q Rev (Acual)'!C15 -> 208235 | D23: =$E$5*(C23/F19)+(1-$E$5)*(D22+E22) -> 198905.97 | E23: =$E$6*(D23-D22)+(1-$E$6)*E22 -> 1980.6375 | F23: =$E$7*(C23/D23)+(1-$E$7)*F19 -> 1.0482346 | G23: =SUM(D22:E22)*F19 -> 211549.58
B24: ='ULTA Q Rev (Acual)'!B16 -> 39478 | C24: ='ULTA Q Rev (Acual)'!C16 -> 309344 | D24: =$E$5*(C24/F20)+(1-$E$5)*(D23+E23) -> 277825.73 | E24: =$E$6*(D24-D23)+(1-$E$6)*E23 -> 5507.45 | F24: =$E$7*(C24/D24)+(1-$E$7)*F20 -> 1.082845 | G24: =SUM(D23:E23)*F20 -> 203051.93
B25: ='ULTA Q Rev (Acual)'!B17 -> 39568 | C25: ='ULTA Q Rev (Acual)'!C17 -> 239298 | D25: =$E$5*(C25/F21)+(1-$E$5)*(D24+E24) -> 252341.66 | E25: =$E$6*(D25-D24)+(1-$E$6)*E24 -> 4086.8297 | F25: =$E$7*(C25/D25)+(1-$E$7)*F21 -> 0.96164254 | G25: =SUM(D24:E24)*F21 -> 281361.75
B26: ='ULTA Q Rev (Acual)'!B18 -> 39660 | C26: ='ULTA Q Rev (Acual)'!C18 -> 249111 | D26: =$E$5*(C26/F22)+(1-$E$5)*(D25+E25) -> 249817.14 | E26: =$E$6*(D26-D25)+(1-$E$6)*E25 -> 3783.772 | F26: =$E$7*(C26/D26)+(1-$E$7)*F22 -> 1.0000866 | G26: =SUM(D25:E25)*F22 -> 258210.02
B27: ='ULTA Q Rev (Acual)'!B19 -> 39752 | C27: ='ULTA Q Rev (Acual)'!C19 -> 254843 | D27: =$E$5*(C27/F23)+(1-$E$5)*(D26+E26) -> 245929.92 | E27: =$E$6*(D27-D26)+(1-$E$6)*E26 -> 3432.1415 | F27: =$E$7*(C27/D27)+(1-$E$7)*F23 -> 1.0398168 | G27: =SUM(D26:E26)*F23 -> 265833.25
B28: ='ULTA Q Rev (Acual)'!B20 -> 39844 | C28: ='ULTA Q Rev (Acual)'!C20 -> 341394 | D28: =$E$5*(C28/F24)+(1-$E$5)*(D27+E27) -> 297587.18 | E28: =$E$6*(D28-D27)+(1-$E$6)*E27 -> 5642.7328 | F28: =$E$7*(C28/D28)+(1-$E$7)*F24 -> 1.128023 | G28: =SUM(D27:E27)*F24 -> 270020.48
... B95: ='ULTA Q Rev (Acual)'!B87 -> 45995 | C95: ='ULTA Q Rev (Acual)'!C87 -> 2857623 | D95: =$E$5*(C95/F91)+(1-$E$5)*(D94+E94) -> 2890225.1 | E95: =$E$6*(D95-D94)+(1-$E$6)*E94 -> 46541.507 | F95: =$E$7*(C95/D95)+(1-$E$7)*F91 -> 0.98860532 | G95: =SUM(D94:E94)*F91 -> 2853484
A96: Forecast | B96: 46108 | G96: =($D$95+$E$95*(ROW()-ROW($G$95)))*F89 -> 3023291.8
B97: 46234 | G97: =($D$95+$E$95*(ROW()-ROW($G$95)))*F90 -> 2899992.8
B98: 46262 | G98: =($D$95+$E$95*(ROW()-ROW($G$95)))*F91 -> 2994508.2
B99: 46360 | G99: =($D$95+$E$95*(ROW()-ROW($G$95)))*F92 -> 4196053.1
B100: 46473 | G100: =($D$95+$E$95*(ROW()-ROW($G$95)))*F93 -> 3252137.1
B101: 46599 | G101: =($D$95+$E$95*(ROW()-ROW($G$95)))*F94 -> 3102139.1
B102: *All figures in thousands of dollars

Sheet ULTA Time Series Reg
B2: ULTA Q Sales Forecasting: Time Series Regression Model
B4: Date | C4: Period | D4: Q1 | E4: Q2 | F4: Q3 | G4: Sales | H4: Fit | J4: SUMMARY OUTPUT
A5: Actual | B5: ='ULTA Q Rev (Acual)'!B5 -> 38472 | C5: 1 | D5: 0 | E5: 0 | F5: 0 | G5: ='ULTA Q Rev (Acual)'!C5 -> 144769 | H5: =$K$20+$K$21*C5+$K$22*D5+$K$23*E5+$K$24*F5 -> -366656.3
B6: ='ULTA Q Rev (Acual)'!B6 -> 38564 | C6: 2 | D6: 1 | E6: =IF(MONTH($B5)=6,1,0) -> 0 | F6: =IF(MONTH($B5)=9,1,0) -> 0 | G6: ='ULTA Q Rev (Acual)'!C6 -> 144769 | H6: =$K$20+$K$21*C6+$K$22*D6+$K$23*E6+$K$24*F6 -> -384535.92 | J6: Regression Statistics
B7: ='ULTA Q Rev (Acual)'!B7 -> 38656 | C7: 3 | D7: 0 | E7: 1 | F7: =IF(MONTH($B6)=9,1,0) -> 0 | G7: ='ULTA Q Rev (Acual)'!C7 -> 144769 | H7: =$K$20+$K$21*C7+$K$22*D7+$K$23*E7+$K$24*F7 -> -356984.79 | J7: Multiple R | K7: 0.95633241
B8: ='ULTA Q Rev (Acual)'!B8 -> 38748 | C8: 4 | D8: =IF(MONTH($B7)=3,1,0) -> 0 | E8: 0 | F8: 1 | G8: ='ULTA Q Rev (Acual)'!C8 -> 144768 | H8: =$K$20+$K$21*C8+$K$22*D8+$K$23*E8+$K$24*F8 -> 57511.208 | J8: R Square | K8: 0.91457169
B9: ='ULTA Q Rev (Acual)'!B9 -> 38837 | C9: 5 | D9: =IF(MONTH($B8)=3,1,0) -> 0 | E9: =IF(MONTH($B8)=6,1,0) -> 0 | F9: 0 | G9: ='ULTA Q Rev (Acual)'!C9 -> 159468 | H9: =$K$20+$K$21*C9+$K$22*D9+$K$23*E9+$K$24*F9 -> -217167.93 | J9: Adjusted R Square | K9: 0.91013385
B10: ='ULTA Q Rev (Acual)'!B10 -> 38929 | C10: 6 | D10: 1 | E10: =IF(MONTH($B9)=6,1,0) -> 0 | F10: =IF(MONTH($B9)=9,1,0) -> 0 | G10: ='ULTA Q Rev (Acual)'!C10 -> 162558 | H10: =$K$20+$K$21*C10+$K$22*D10+$K$23*E10+$K$24*F10 -> -235047.55 | J10: Standard Error | K10: 283650.62
B11: ='ULTA Q Rev (Acual)'!B11 -> 39021 | C11: 7 | D11: 0 | E11: 1 | F11: =IF(MONTH($B10)=9,1,0) -> 0 | G11: ='ULTA Q Rev (Acual)'!C11 -> 216544 | H11: =$K$20+$K$21*C11+$K$22*D11+$K$23*E11+$K$24*F11 -> -207496.42 | J11: Observations | K11: 82
B12: ='ULTA Q Rev (Acual)'!B12 -> 39113 | C12: 8 | D12: =IF(MONTH($B11)=3,1,0) -> 0 | E12: 0 | F12: 1 | G12: ='ULTA Q Rev (Acual)'!C12 -> 216543 | H12: =$K$20+$K$21*C12+$K$22*D12+$K$23*E12+$K$24*F12 -> 206999.58
B13: ='ULTA Q Rev (Acual)'!B13 -> 39202 | C13: 9 | D13: =IF(MONTH($B12)=3,1,0) -> 0 | E13: =IF(MONTH($B12)=6,1,0) -> 0 | F13: 0 | G13: ='ULTA Q Rev (Acual)'!C13 -> 194113 | H13: =$K$20+$K$21*C13+$K$22*D13+$K$23*E13+$K$24*F13 -> -67679.554 | J13: ANOVA
B14: ='ULTA Q Rev (Acual)'!B14 -> 39293 | C14: 10 | D14: 1 | E14: =IF(MONTH($B13)=6,1,0) -> 0 | F14: =IF(MONTH($B13)=9,1,0) -> 0 | G14: ='ULTA Q Rev (Acual)'!C14 -> 200449 | H14: =$K$20+$K$21*C14+$K$22*D14+$K$23*E14+$K$24*F14 -> -85559.173 | K14: df | L14: SS | M14: MS | N14: F | O14: Significance F
B15: ='ULTA Q Rev (Acual)'!B15 -> 39386 | C15: 11 | D15: 0 | E15: 1 | F15: =IF(MONTH($B14)=9,1,0) -> 0 | G15: ='ULTA Q Rev (Acual)'!C15 -> 208235 | H15: =$K$20+$K$21*C15+$K$22*D15+$K$23*E15+$K$24*F15 -> -58008.046 | J15: Regression | K15: 4 | L15: 6.6324521e+13 | M15: 1.658113e+13 | N15: 206.08513 | O15: 2.6638591e-40
B16: ='ULTA Q Rev (Acual)'!B16 -> 39478 | C16: 12 | D16: =IF(MONTH($B15)=3,1,0) -> 0 | E16: 0 | F16: 1 | G16: ='ULTA Q Rev (Acual)'!C16 -> 309344 | H16: =$K$20+$K$21*C16+$K$22*D16+$K$23*E16+$K$24*F16 -> 356487.95 | J16: Residual | K16: 77 | L16: 6.195241e+12 | M16: 8.0457675e+10
B17: ='ULTA Q Rev (Acual)'!B17 -> 39568 | C17: 13 | D17: =IF(MONTH($B16)=3,1,0) -> 0 | E17: =IF(MONTH($B16)=6,1,0) -> 0 | F17: 0 | G17: ='ULTA Q Rev (Acual)'!C17 -> 239298 | H17: =$K$20+$K$21*C17+$K$22*D17+$K$23*E17+$K$24*F17 -> 81808.819 | J17: Total | K17: 81 | L17: 7.2519762e+13
B18: ='ULTA Q Rev (Acual)'!B18 -> 39660 | C18: 14 | D18: 1 | E18: =IF(MONTH($B17)=6,1,0) -> 0 | F18: =IF(MONTH($B17)=9,1,0) -> 0 | G18: ='ULTA Q Rev (Acual)'!C18 -> 249111 | H18: =$K$20+$K$21*C18+$K$22*D18+$K$23*E18+$K$24*F18 -> 63929.2
B19: ='ULTA Q Rev (Acual)'!B19 -> 39752 | C19: 15 | D19: 0 | E19: 1 | F19: =IF(MONTH($B18)=9,1,0) -> 0 | G19: ='ULTA Q Rev (Acual)'!C19 -> 254843 | H19: =$K$20+$K$21*C19+$K$22*D19+$K$23*E19+$K$24*F19 -> 91480.327 | K19: Coefficients | L19: Standard Error | M19: t Stat | N19: P-value | O19: Lower 95% | P19: Upper 95% | Q19: Lower 95.0% | R19: Upper 95.0%
B20: ='ULTA Q Rev (Acual)'!B20 -> 39844 | C20: 16 | D20: =IF(MONTH($B19)=3,1,0) -> 0 | E20: 0 | F20: 1 | G20: ='ULTA Q Rev (Acual)'!C20 -> 341394 | H20: =$K$20+$K$21*C20+$K$22*D20+$K$23*E20+$K$24*F20 -> 505976.33 | J20: Intercept | K20: -404028.39 | L20: 82320.371 | M20: -4.9080001 | N20: 5.0292628e-06 | O20: -567949.19 | P20: -240107.59 | Q20: -567949.19 | R20: -240107.59
B21: ='ULTA Q Rev (Acual)'!B21 -> 39933 | C21: 17 | D21: =IF(MONTH($B20)=3,1,0) -> 0 | E21: =IF(MONTH($B20)=6,1,0) -> 0 | F21: 0 | G21: ='ULTA Q Rev (Acual)'!C21 -> 268825 | H21: =$K$20+$K$21*C21+$K$22*D21+$K$23*E21+$K$24*F21 -> 231297.19 | J21: Period | K21: 37372.093 | L21: 1323.6794 | M21: 28.233494 | N21: 2.2698199e-42 | O21: 34736.311 | P21: 40007.876 | Q21: 34736.311 | R21: 40007.876
B22: ='ULTA Q Rev (Acual)'!B22 -> 40025 | C22: 18 | D22: 1 | E22: =IF(MONTH($B21)=6,1,0) -> 0 | F22: =IF(MONTH($B21)=9,1,0) -> 0 | G22: ='ULTA Q Rev (Acual)'!C22 -> 273539 | H22: =$K$20+$K$21*C22+$K$22*D22+$K$23*E22+$K$24*F22 -> 213417.57 | J22: Q1 | K22: -55251.712 | L22: 87546.49 | M22: -0.63111282 | N22: 0.52983574 | O22: -229579.04 | P22: 119075.62 | Q22: -229579.04 | R22: 119075.62
B23: ='ULTA Q Rev (Acual)'!B23 -> 40117 | C23: 19 | D23: 0 | E23: 1 | F23: =IF(MONTH($B22)=9,1,0) -> 0 | G23: ='ULTA Q Rev (Acual)'!C23 -> 284043 | H23: =$K$20+$K$21*C23+$K$22*D23+$K$23*E23+$K$24*F23 -> 240968.7 | J23: Q2 | K23: -65072.679 | L23: 88623.934 | M23: -0.73425626 | N23: 0.46502267 | O23: -241545.48 | P23: 111400.12 | Q23: -241545.48 | R23: 111400.12
B24: ='ULTA Q Rev (Acual)'!B24 -> 40209 | C24: 20 | D24: =IF(MONTH($B23)=3,1,0) -> 0 | E24: 0 | F24: 1 | G24: ='ULTA Q Rev (Acual)'!C24 -> 396364 | H24: =$K$20+$K$21*C24+$K$22*D24+$K$23*E24+$K$24*F24 -> 655464.7 | J24: Q3 | K24: 312051.23 | L24: 88633.818 | M24: 3.5206791 | N24: 0.00072670779 | O24: 135558.75 | P24: 488543.71 | Q24: 135558.75 | R24: 488543.71
B25: ='ULTA Q Rev (Acual)'!B25 -> 40298 | C25: 21 | D25: 0 | E25: 0 | F25: 0 | G25: ='ULTA Q Rev (Acual)'!C25 -> 320196 | H25: =$K$20+$K$21*C25+$K$22*D25+$K$23*E25+$K$24*F25 -> 380785.56
B26: ='ULTA Q Rev (Acual)'!B26 -> 40390 | C26: 22 | D26: 1 | E26: =IF(MONTH($B25)=6,1,0) -> 0 | F26: =IF(MONTH($B25)=9,1,0) -> 0 | G26: ='ULTA Q Rev (Acual)'!C26 -> 321804 | H26: =$K$20+$K$21*C26+$K$22*D26+$K$23*E26+$K$24*F26 -> 362905.95
B27: ='ULTA Q Rev (Acual)'!B27 -> 40482 | C27: 23 | D27: 0 | E27: 1 | F27: =IF(MONTH($B26)=9,1,0) -> 0 | G27: ='ULTA Q Rev (Acual)'!C27 -> 339179 | H27: =$K$20+$K$21*C27+$K$22*D27+$K$23*E27+$K$24*F27 -> 390457.07
B28: ='ULTA Q Rev (Acual)'!B28 -> 40574 | C28: 24 | D28: =IF(MONTH($B27)=3,1,0) -> 0 | E28: 0 | F28: 1 | G28: ='ULTA Q Rev (Acual)'!C28 -> 473659 | H28: =$K$20+$K$21*C28+$K$22*D28+$K$23*E28+$K$24*F28 -> 804953.07
B29: ='ULTA Q Rev (Acual)'!B29 -> 40663 | C29: 25 | D29: =IF(MONTH($B28)=3,1,0) -> 0 | E29: =IF(MONTH($B28)=6,1,0) -> 0 | F29: 0 | G29: ='ULTA Q Rev (Acual)'!C29 -> 386006 | H29: =$K$20+$K$21*C29+$K$22*D29+$K$23*E29+$K$24*F29 -> 530273.94
B30: ='ULTA Q Rev (Acual)'!B30 -> 40755 | C30: 26 | D30: 1 | E30: =IF(MONTH($B29)=6,1,0) -> 0 | F30: =IF(MONTH($B29)=9,1,0) -> 0 | G30: ='ULTA Q Rev (Acual)'!C30 -> 394567 | H30: =$K$20+$K$21*C30+$K$22*D30+$K$23*E30+$K$24*F30 -> 512394.32
B31: ='ULTA Q Rev (Acual)'!B31 -> 40847 | C31: 27 | D31: 0 | E31: 1 | F31: =IF(MONTH($B30)=9,1,0) -> 0 | G31: ='ULTA Q Rev (Acual)'!C31 -> 413067 | H31: =$K$20+$K$21*C31+$K$22*D31+$K$23*E31+$K$24*F31 -> 539945.45
B32: ='ULTA Q Rev (Acual)'!B32 -> 40939 | C32: 28 | D32: =IF(MONTH($B31)=3,1,0) -> 0 | E32: 0 | F32: 1 | G32: ='ULTA Q Rev (Acual)'!C32 -> 582511 | H32: =$K$20+$K$21*C32+$K$22*D32+$K$23*E32+$K$24*F32 -> 954441.45
B33: ='ULTA Q Rev (Acual)'!B33 -> 41029 | C33: 29 | D33: =IF(MONTH($B32)=3,1,0) -> 0 | E33: =IF(MONTH($B32)=6,1,0) -> 0 | F33: 0 | G33: ='ULTA Q Rev (Acual)'!C33 -> 474098 | H33: =$K$20+$K$21*C33+$K$22*D33+$K$23*E33+$K$24*F33 -> 679762.31
B34: ='ULTA Q Rev (Acual)'!B34 -> 41121 | C34: 30 | D34: 1 | E34: =IF(MONTH($B33)=6,1,0) -> 0 | F34: =IF(MONTH($B33)=9,1,0) -> 0 | G34: ='ULTA Q Rev (Acual)'!C34 -> 481683 | H34: =$K$20+$K$21*C34+$K$22*D34+$K$23*E34+$K$24*F34 -> 661882.69
B35: ='ULTA Q Rev (Acual)'!B35 -> 41213 | C35: 31 | D35: 0 | E35: 1 | F35: =IF(MONTH($B34)=9,1,0) -> 0 | G35: ='ULTA Q Rev (Acual)'!C35 -> 505640 | H35: =$K$20+$K$21*C35+$K$22*D35+$K$23*E35+$K$24*F35 -> 689433.82
B36: ='ULTA Q Rev (Acual)'!B36 -> 41365 | C36: 32 | D36: =IF(MONTH($B35)=3,1,0) -> 0 | E36: 0 | F36: 1 | G36: ='ULTA Q Rev (Acual)'!C36 -> 758835 | H36: =$K$20+$K$21*C36+$K$22*D36+$K$23*E36+$K$24*F36 -> 1103929.8
B37: ='ULTA Q Rev (Acual)'!B37 -> 41435 | C37: 33 | D37: =IF(MONTH($B36)=3,1,0) -> 0 | E37: =IF(MONTH($B36)=6,1,0) -> 0 | F37: 0 | G37: ='ULTA Q Rev (Acual)'!C37 -> 582712 | H37: =$K$20+$K$21*C37+$K$22*D37+$K$23*E37+$K$24*F37 -> 829250.68
B38: ='ULTA Q Rev (Acual)'!B38 -> 41528 | C38: 34 | D38: 1 | E38: 0 | F38: =IF(MONTH($B37)=9,1,0) -> 0 | G38: ='ULTA Q Rev (Acual)'!C38 -> 600998 | H38: =$K$20+$K$21*C38+$K$22*D38+$K$23*E38+$K$24*F38 -> 811371.06
B39: ='ULTA Q Rev (Acual)'!B39 -> 41612 | C39: 35 | D39: 0 | E39: 1 | F39: 0 | G39: ='ULTA Q Rev (Acual)'!C39 -> 618781 | H39: =$K$20+$K$21*C39+$K$22*D39+$K$23*E39+$K$24*F39 -> 838922.19
B40: ='ULTA Q Rev (Acual)'!B40 -> 41728 | C40: 36 | D40: =IF(MONTH($B39)=3,1,0) -> 0 | E40: 0 | F40: 1 | G40: ='ULTA Q Rev (Acual)'!C40 -> 868082 | H40: =$K$20+$K$21*C40+$K$22*D40+$K$23*E40+$K$24*F40 -> 1253418.2
B41: ='ULTA Q Rev (Acual)'!B41 -> 41794 | C41: 37 | D41: 0 | E41: 0 | F41: 0 | G41: ='ULTA Q Rev (Acual)'!C41 -> 713770 | H41: =$K$20+$K$21*C41+$K$22*D41+$K$23*E41+$K$24*F41 -> 978739.06
B42: ='ULTA Q Rev (Acual)'!B42 -> 41823 | C42: 38 | D42: 1 | E42: 0 | F42: =IF(MONTH($B41)=9,1,0) -> 0 | G42: ='ULTA Q Rev (Acual)'!C42 -> 734236 | H42: =$K$20+$K$21*C42+$K$22*D42+$K$23*E42+$K$24*F42 -> 960859.44
B43: ='ULTA Q Rev (Acual)'!B43 -> 41976 | C43: 39 | D43: 0 | E43: 1 | F43: =IF(MONTH($B42)=9,1,0) -> 0 | G43: ='ULTA Q Rev (Acual)'!C43 -> 745722 | H43: =$K$20+$K$21*C43+$K$22*D43+$K$23*E43+$K$24*F43 -> 988410.56
B44: ='ULTA Q Rev (Acual)'!B44 -> 42091 | C44: 40 | D44: =IF(MONTH($B43)=3,1,0) -> 0 | E44: 0 | F44: 1 | G44: ='ULTA Q Rev (Acual)'!C44 -> 1047641 | H44: =$K$20+$K$21*C44+$K$22*D44+$K$23*E44+$K$24*F44 -> 1402906.6
B45: ='ULTA Q Rev (Acual)'!B45 -> 42157 | C45: 41 | D45: 0 | E45: 0 | F45: 0 | G45: ='ULTA Q Rev (Acual)'!C45 -> 868122 | H45: =$K$20+$K$21*C45+$K$22*D45+$K$23*E45+$K$24*F45 -> 1128227.4
B46: ='ULTA Q Rev (Acual)'!B46 -> 42241 | C46: 42 | D46: 1 | E46: 0 | F46: =IF(MONTH($B45)=9,1,0) -> 0 | G46: ='ULTA Q Rev (Acual)'!C46 -> 876999 | H46: =$K$20+$K$21*C46+$K$22*D46+$K$23*E46+$K$24*F46 -> 1110347.8
B47: ='ULTA Q Rev (Acual)'!B47 -> 42339 | C47: 43 | D47: 0 | E47: 1 | F47: =IF(MONTH($B46)=9,1,0) -> 0 | G47: ='ULTA Q Rev (Acual)'!C47 -> 910700 | H47: =$K$20+$K$21*C47+$K$22*D47+$K$23*E47+$K$24*F47 -> 1137898.9
B48: ='ULTA Q Rev (Acual)'!B48 -> 42463 | C48: 44 | D48: =IF(MONTH($B47)=3,1,0) -> 0 | E48: 0 | F48: 1 | G48: ='ULTA Q Rev (Acual)'!C48 -> 1268295 | H48: =$K$20+$K$21*C48+$K$22*D48+$K$23*E48+$K$24*F48 -> 1552394.9
B49: ='ULTA Q Rev (Acual)'!B49 -> 42522 | C49: 45 | D49: =IF(MONTH($B48)=3,1,0) -> 0 | E49: =IF(MONTH($B48)=6,1,0) -> 0 | F49: 0 | G49: ='ULTA Q Rev (Acual)'!C49 -> 1073716 | H49: =$K$20+$K$21*C49+$K$22*D49+$K$23*E49+$K$24*F49 -> 1277715.8
B50: ='ULTA Q Rev (Acual)'!B50 -> 42613 | C50: 46 | D50: 1 | E50: 0 | F50: =IF(MONTH($B49)=9,1,0) -> 0 | G50: ='ULTA Q Rev (Acual)'!C50 -> 1069215 | H50: =$K$20+$K$21*C50+$K$22*D50+$K$23*E50+$K$24*F50 -> 1259836.2
B51: ='ULTA Q Rev (Acual)'!B51 -> 42704 | C51: 47 | D51: 0 | E51: 1 | F51: =IF(MONTH($B50)=9,1,0) -> 0 | G51: ='ULTA Q Rev (Acual)'!C51 -> 1131232 | H51: =$K$20+$K$21*C51+$K$22*D51+$K$23*E51+$K$24*F51 -> 1287387.3
B52: ='ULTA Q Rev (Acual)'!B52 -> 42827 | C52: 48 | D52: =IF(MONTH($B51)=3,1,0) -> 0 | E52: 0 | F52: 1 | G52: ='ULTA Q Rev (Acual)'!C52 -> 1580574 | H52: =$K$20+$K$21*C52+$K$22*D52+$K$23*E52+$K$24*F52 -> 1701883.3
B53: ='ULTA Q Rev (Acual)'!B53 -> 42887 | C53: 49 | D53: =IF(MONTH($B52)=3,1,0) -> 0 | E53: =IF(MONTH($B52)=6,1,0) -> 0 | F53: 0 | G53: ='ULTA Q Rev (Acual)'!C53 -> 1314879 | H53: =$K$20+$K$21*C53+$K$22*D53+$K$23*E53+$K$24*F53 -> 1427204.2
B54: ='ULTA Q Rev (Acual)'!B54 -> 42977 | C54: 50 | D54: 1 | E54: 0 | F54: =IF(MONTH($B53)=9,1,0) -> 0 | G54: ='ULTA Q Rev (Acual)'!C54 -> 1289854 | H54: =$K$20+$K$21*C54+$K$22*D54+$K$23*E54+$K$24*F54 -> 1409324.6
B55: ='ULTA Q Rev (Acual)'!B55 -> 43075 | C55: 51 | D55: 0 | E55: 1 | F55: =IF(MONTH($B54)=9,1,0) -> 0 | G55: ='ULTA Q Rev (Acual)'!C55 -> 1342181 | H55: =$K$20+$K$21*C55+$K$22*D55+$K$23*E55+$K$24*F55 -> 1436875.7
B56: ='ULTA Q Rev (Acual)'!B56 -> 43186 | C56: 52 | D56: =IF(MONTH($B55)=3,1,0) -> 0 | E56: 0 | F56: 1 | G56: ='ULTA Q Rev (Acual)'!C56 -> 1937592 | H56: =$K$20+$K$21*C56+$K$22*D56+$K$23*E56+$K$24*F56 -> 1851371.7
B57: ='ULTA Q Rev (Acual)'!B57 -> 43250 | C57: 53 | D57: 0 | E57: 0 | F57: 0 | G57: ='ULTA Q Rev (Acual)'!C57 -> 1543667 | H57: =$K$20+$K$21*C57+$K$22*D57+$K$23*E57+$K$24*F57 -> 1576692.5
B58: ='ULTA Q Rev (Acual)'!B58 -> 43341 | C58: 54 | D58: 1 | E58: =IF(MONTH($B57)=6,1,0) -> 0 | F58: =IF(MONTH($B57)=9,1,0) -> 0 | G58: ='ULTA Q Rev (Acual)'!C58 -> 1488221 | H58: =$K$20+$K$21*C58+$K$22*D58+$K$23*E58+$K$24*F58 -> 1558812.9
B59: ='ULTA Q Rev (Acual)'!B59 -> 43439 | C59: 55 | D59: 0 | E59: 1 | F59: =IF(MONTH($B58)=9,1,0) -> 0 | G59: ='ULTA Q Rev (Acual)'!C59 -> 1560011 | H59: =$K$20+$K$21*C59+$K$22*D59+$K$23*E59+$K$24*F59 -> 1586364.1
B60: ='ULTA Q Rev (Acual)'!B60 -> 43550 | C60: 56 | D60: =IF(MONTH($B59)=3,1,0) -> 0 | E60: 0 | F60: 1 | G60: ='ULTA Q Rev (Acual)'!C60 -> 2124716 | H60: =$K$20+$K$21*C60+$K$22*D60+$K$23*E60+$K$24*F60 -> 2000860.1
B61: ='ULTA Q Rev (Acual)'!B61 -> 43613 | C61: 57 | D61: 0 | E61: 0 | F61: 0 | G61: ='ULTA Q Rev (Acual)'!C61 -> 1743029 | H61: =$K$20+$K$21*C61+$K$22*D61+$K$23*E61+$K$24*F61 -> 1726180.9
B62: ='ULTA Q Rev (Acual)'!B62 -> 43704 | C62: 58 | D62: 1 | E62: =IF(MONTH($B61)=6,1,0) -> 0 | F62: =IF(MONTH($B61)=9,1,0) -> 0 | G62: ='ULTA Q Rev (Acual)'!C62 -> 1666607 | H62: =$K$20+$K$21*C62+$K$22*D62+$K$23*E62+$K$24*F62 -> 1708301.3
B63: ='ULTA Q Rev (Acual)'!B63 -> 43802 | C63: 59 | D63: 0 | E63: 1 | F63: =IF(MONTH($B62)=9,1,0) -> 0 | G63: ='ULTA Q Rev (Acual)'!C63 -> 1682514 | H63: =$K$20+$K$21*C63+$K$22*D63+$K$23*E63+$K$24*F63 -> 1735852.4
B64: ='ULTA Q Rev (Acual)'!B64 -> 43915 | C64: 60 | D64: =IF(MONTH($B63)=3,1,0) -> 0 | E64: 0 | F64: 1 | G64: ='ULTA Q Rev (Acual)'!C64 -> 2305918 | H64: =$K$20+$K$21*C64+$K$22*D64+$K$23*E64+$K$24*F64 -> 2150348.4
B65: ='ULTA Q Rev (Acual)'!B65 -> 43978 | C65: 61 | D65: 0 | E65: 0 | F65: 0 | G65: ='ULTA Q Rev (Acual)'!C65 -> 1173210 | H65: =$K$20+$K$21*C65+$K$22*D65+$K$23*E65+$K$24*F65 -> 1875669.3
B66: ='ULTA Q Rev (Acual)'!B66 -> 44068 | C66: 62 | D66: 1 | E66: =IF(MONTH($B65)=6,1,0) -> 0 | F66: =IF(MONTH($B65)=9,1,0) -> 0 | G66: ='ULTA Q Rev (Acual)'!C66 -> 1228009 | H66: =$K$20+$K$21*C66+$K$22*D66+$K$23*E66+$K$24*F66 -> 1857789.7
B67: ='ULTA Q Rev (Acual)'!B67 -> 44167 | C67: 63 | D67: 0 | E67: 1 | F67: =IF(MONTH($B66)=9,1,0) -> 0 | G67: ='ULTA Q Rev (Acual)'!C67 -> 1552033 | H67: =$K$20+$K$21*C67+$K$22*D67+$K$23*E67+$K$24*F67 -> 1885340.8
B68: ='ULTA Q Rev (Acual)'!B68 -> 44279 | C68: 64 | D68: =IF(MONTH($B67)=3,1,0) -> 0 | E68: 0 | F68: 1 | G68: ='ULTA Q Rev (Acual)'!C68 -> 2198701 | H68: =$K$20+$K$21*C68+$K$22*D68+$K$23*E68+$K$24*F68 -> 2299836.8
B69: ='ULTA Q Rev (Acual)'!B69 -> 44342 | C69: 65 | D69: 0 | E69: 0 | F69: 0 | G69: ='ULTA Q Rev (Acual)'!C69 -> 1938519 | H69: =$K$20+$K$21*C69+$K$22*D69+$K$23*E69+$K$24*F69 -> 2025157.7
B70: ='ULTA Q Rev (Acual)'!B70 -> 44433 | C70: 66 | D70: 1 | E70: =IF(MONTH($B69)=6,1,0) -> 0 | F70: =IF(MONTH($B69)=9,1,0) -> 0 | G70: ='ULTA Q Rev (Acual)'!C70 -> 1967207 | H70: =$K$20+$K$21*C70+$K$22*D70+$K$23*E70+$K$24*F70 -> 2007278
B71: ='ULTA Q Rev (Acual)'!B71 -> 44531 | C71: 67 | D71: 0 | E71: 1 | F71: =IF(MONTH($B70)=9,1,0) -> 0 | G71: ='ULTA Q Rev (Acual)'!C71 -> 1995775 | H71: =$K$20+$K$21*C71+$K$22*D71+$K$23*E71+$K$24*F71 -> 2034829.2
B72: ='ULTA Q Rev (Acual)'!B72 -> 44646 | C72: 68 | D72: =IF(MONTH($B71)=3,1,0) -> 0 | E72: 0 | F72: 1 | G72: ='ULTA Q Rev (Acual)'!C72 -> 2729388 | H72: =$K$20+$K$21*C72+$K$22*D72+$K$23*E72+$K$24*F72 -> 2449325.2
B73: ='ULTA Q Rev (Acual)'!B73 -> 44706 | C73: 69 | D73: 0 | E73: 0 | F73: 0 | G73: ='ULTA Q Rev (Acual)'!C73 -> 2345901 | H73: =$K$20+$K$21*C73+$K$22*D73+$K$23*E73+$K$24*F73 -> 2174646
B74: ='ULTA Q Rev (Acual)'!B74 -> 44797 | C74: 70 | D74: 1 | E74: =IF(MONTH($B73)=6,1,0) -> 0 | F74: =IF(MONTH($B73)=9,1,0) -> 0 | G74: ='ULTA Q Rev (Acual)'!C74 -> 2297113 | H74: =$K$20+$K$21*C74+$K$22*D74+$K$23*E74+$K$24*F74 -> 2156766.4
B75: ='ULTA Q Rev (Acual)'!B75 -> 44895 | C75: 71 | D75: 0 | E75: 1 | F75: =IF(MONTH($B74)=9,1,0) -> 0 | G75: ='ULTA Q Rev (Acual)'!C75 -> 2338793 | H75: =$K$20+$K$21*C75+$K$22*D75+$K$23*E75+$K$24*F75 -> 2184317.5
B76: ='ULTA Q Rev (Acual)'!B76 -> 45012 | C76: 72 | D76: =IF(MONTH($B75)=3,1,0) -> 0 | E76: 0 | F76: 1 | G76: ='ULTA Q Rev (Acual)'!C76 -> 3226773 | H76: =$K$20+$K$21*C76+$K$22*D76+$K$23*E76+$K$24*F76 -> 2598813.5
B77: ='ULTA Q Rev (Acual)'!B77 -> 45076 | C77: 73 | D77: 0 | E77: 0 | F77: 0 | G77: ='ULTA Q Rev (Acual)'!C77 -> 2634263 | H77: =$K$20+$K$21*C77+$K$22*D77+$K$23*E77+$K$24*F77 -> 2324134.4
B78: ='ULTA Q Rev (Acual)'!B78 -> 45167 | C78: 74 | D78: 1 | E78: =IF(MONTH($B77)=6,1,0) -> 0 | F78: =IF(MONTH($B77)=9,1,0) -> 0 | G78: ='ULTA Q Rev (Acual)'!C78 -> 2529809 | H78: =$K$20+$K$21*C78+$K$22*D78+$K$23*E78+$K$24*F78 -> 2306254.8
B79: ='ULTA Q Rev (Acual)'!B79 -> 45265 | C79: 75 | D79: 0 | E79: 1 | F79: =IF(MONTH($B78)=9,1,0) -> 0 | G79: ='ULTA Q Rev (Acual)'!C79 -> 2488933 | H79: =$K$20+$K$21*C79+$K$22*D79+$K$23*E79+$K$24*F79 -> 2333805.9
B80: ='ULTA Q Rev (Acual)'!B80 -> 45378 | C80: 76 | D80: =IF(MONTH($B79)=3,1,0) -> 0 | E80: 0 | F80: 1 | G80: ='ULTA Q Rev (Acual)'!C80 -> 3554298 | H80: =$K$20+$K$21*C80+$K$22*D80+$K$23*E80+$K$24*F80 -> 2748301.9
B81: ='ULTA Q Rev (Acual)'!B81 -> 45441 | C81: 77 | D81: 0 | E81: 0 | F81: 0 | G81: ='ULTA Q Rev (Acual)'!C81 -> 2725848 | H81: =$K$20+$K$21*C81+$K$22*D81+$K$23*E81+$K$24*F81 -> 2473622.8
B82: ='ULTA Q Rev (Acual)'!B82 -> 45532 | C82: 78 | D82: 1 | E82: =IF(MONTH($B81)=6,1,0) -> 0 | F82: =IF(MONTH($B81)=9,1,0) -> 0 | G82: ='ULTA Q Rev (Acual)'!C82 -> 2552087 | H82: =$K$20+$K$21*C82+$K$22*D82+$K$23*E82+$K$24*F82 -> 2455743.2
B83: ='ULTA Q Rev (Acual)'!B83 -> 45631 | C83: 79 | D83: 0 | E83: 1 | F83: =IF(MONTH($B82)=9,1,0) -> 0 | G83: ='ULTA Q Rev (Acual)'!C83 -> 2530100 | H83: =$K$20+$K$21*C83+$K$22*D83+$K$23*E83+$K$24*F83 -> 2483294.3
B84: ='ULTA Q Rev (Acual)'!B84 -> 45743 | C84: 80 | D84: =IF(MONTH($B83)=3,1,0) -> 0 | E84: 0 | F84: 1 | G84: ='ULTA Q Rev (Acual)'!C84 -> 3487619 | H84: =$K$20+$K$21*C84+$K$22*D84+$K$23*E84+$K$24*F84 -> 2897790.3
B85: ='ULTA Q Rev (Acual)'!B85 -> 45806 | C85: 81 | D85: 0 | E85: 0 | F85: 0 | G85: ='ULTA Q Rev (Acual)'!C85 -> 2848367 | H85: =$K$20+$K$21*C85+$K$22*D85+$K$23*E85+$K$24*F85 -> 2623111.2
B86: ='ULTA Q Rev (Acual)'!B86 -> 45897 | C86: 82 | D86: 1 | E86: 0 | F86: 0 | G86: ='ULTA Q Rev (Acual)'!C86 -> 2788469 | H86: =$K$20+$K$21*C86+$K$22*D86+$K$23*E86+$K$24*F86 -> 2605231.5
B87: ='ULTA Q Rev (Acual)'!B87 -> 45995 | C87: 83 | D87: 0 | E87: 1 | F87: =IF(MONTH($B85)=9,1,0) -> 0 | G87: ='ULTA Q Rev (Acual)'!C87 -> 2857623 | H87: =$K$20+$K$21*C87+$K$22*D87+$K$23*E87+$K$24*F87 -> 2632782.7
A88: Forecast | B88: 46108 | C88: 84 | D88: 0 | E88: 0 | F88: 1 | H88: =$K$20+$K$21*C88+$K$22*D88+$K$23*E88+$K$24*F88 -> 3047278.7
B89: 46234 | C89: 85 | D89: 0 | E89: 0 | F89: 0 | H89: =$K$20+$K$21*C89+$K$22*D89+$K$23*E89+$K$24*F89 -> 2772599.5
B90: 46262 | C90: 86 | D90: 1 | E90: 0 | F90: 0 | H90: =$K$20+$K$21*C90+$K$22*D90+$K$23*E90+$K$24*F90 -> 2754719.9
B91: 46360 | C91: 87 | D91: 0 | E91: 1 | F91: =IF(MONTH($B90)=9,1,0) -> 0 | H91: =$K$20+$K$21*C91+$K$22*D91+$K$23*E91+$K$24*F91 -> 2782271
B92: 46473 | C92: 88 | D92: 0 | E92: 0 | F92: 1 | H92: =$K$20+$K$21*C92+$K$22*D92+$K$23*E92+$K$24*F92 -> 3196767
B93: 46599 | C93: 89 | D93: 0 | E93: 0 | F93: 0 | H93: =$K$20+$K$21*C93+$K$22*D93+$K$23*E93+$K$24*F93 -> 2922087.9
B94: *All figures in thousands of dollars

Sheet ULTA ETS
B2: Error Trend Seasonal (ETS) for Scenario Analysis
B4: Date | C4: Sales | D4: Forecast | E4: Lower Confidence Bound | F4: Upper Confidence Bound
B5: ='ULTA Q Rev (Acual)'!B5 -> 38472 | C5: ='ULTA Q Rev (Acual)'!C5 -> 144769
B6: ='ULTA Q Rev (Acual)'!B6 -> 38564 | C6: ='ULTA Q Rev (Acual)'!C6 -> 144769
B7: ='ULTA Q Rev (Acual)'!B7 -> 38656 | C7: ='ULTA Q Rev (Acual)'!C7 -> 144769
B8: ='ULTA Q Rev (Acual)'!B8 -> 38748 | C8: ='ULTA Q Rev (Acual)'!C8 -> 144768
B9: ='ULTA Q Rev (Acual)'!B9 -> 38837 | C9: ='ULTA Q Rev (Acual)'!C9 -> 159468
B10: ='ULTA Q Rev (Acual)'!B10 -> 38929 | C10: ='ULTA Q Rev (Acual)'!C10 -> 162558
B11: ='ULTA Q Rev (Acual)'!B11 -> 39021 | C11: ='ULTA Q Rev (Acual)'!C11 -> 216544
B12: ='ULTA Q Rev (Acual)'!B12 -> 39113 | C12: ='ULTA Q Rev (Acual)'!C12 -> 216543
B13: ='ULTA Q Rev (Acual)'!B13 -> 39202 | C13: ='ULTA Q Rev (Acual)'!C13 -> 194113
B14: ='ULTA Q Rev (Acual)'!B14 -> 39293 | C14: ='ULTA Q Rev (Acual)'!C14 -> 200449
B15: ='ULTA Q Rev (Acual)'!B15 -> 39386 | C15: ='ULTA Q Rev (Acual)'!C15 -> 208235
B16: ='ULTA Q Rev (Acual)'!B16 -> 39478 | C16: ='ULTA Q Rev (Acual)'!C16 -> 309344
... B86: ='ULTA Q Rev (Acual)'!B86 -> 45897 | C86: ='ULTA Q Rev (Acual)'!C86 -> 2788469
B87: ='ULTA Q Rev (Acual)'!B87 -> 45995 | C87: ='ULTA Q Rev (Acual)'!C87 -> 2857623 | D87: =Table3[[#This Row],[Sales]] -> 2857623 | E87: =Table3[[#This Row],[Forecast]] -> 2857623 | F87: =Table3[[#This Row],[Lower Confidence Bound]] -> 2857623
B88: 46108 | D88: =_xlfn.FORECAST.ETS(B88,$C$5:$C$87,$B$5:$B$87,1,1) -> 3124932.9 | E88: =D88-_xlfn.FORECAST.ETS.CONFINT(B88,$C$5:$C$87,$B$5:$B$87,0.95,1,1) -> 2855144.2 | F88: =D88+_xlfn.FORECAST.ETS.CONFINT(B88,$C$5:$C$87,$B$5:$B$87,0.95,1,1) -> 3394721.7
B89: 46234 | D89: =_xlfn.FORECAST.ETS(B89,$C$5:$C$87,$B$5:$B$87,1,1) -> 3015598 | E89: =D89-_xlfn.FORECAST.ETS.CONFINT(B89,$C$5:$C$87,$B$5:$B$87,0.95,1,1) -> 2630942.2 | F89: =D89+_xlfn.FORECAST.ETS.CONFINT(B89,$C$5:$C$87,$B$5:$B$87,0.95,1,1) -> 3400253.9
B90: 46262 | D90: =_xlfn.FORECAST.ETS(B90,$C$5:$C$87,$B$5:$B$87,1,1) -> 2925789.3 | E90: =D90-_xlfn.FORECAST.ETS.CONFINT(B90,$C$5:$C$87,$B$5:$B$87,0.95,1,1) -> 2518031.2 | F90: =D90+_xlfn.FORECAST.ETS.CONFINT(B90,$C$5:$C$87,$B$5:$B$87,0.95,1,1) -> 3333547.4
B91: 46360 | D91: =_xlfn.FORECAST.ETS(B91,$C$5:$C$87,$B$5:$B$87,1,1) -> 3043106.1 | E91: =D91-_xlfn.FORECAST.ETS.CONFINT(B91,$C$5:$C$87,$B$5:$B$87,0.95,1,1) -> 2551744.5 | F91: =D91+_xlfn.FORECAST.ETS.CONFINT(B91,$C$5:$C$87,$B$5:$B$87,0.95,1,1) -> 3534467.8
B92: 46473 | D92: =_xlfn.FORECAST.ETS(B92,$C$5:$C$87,$B$5:$B$87,1,1) -> 3302646.6 | E92: =D92-_xlfn.FORECAST.ETS.CONFINT(B92,$C$5:$C$87,$B$5:$B$87,0.95,1,1) -> 2703549.7 | F92: =D92+_xlfn.FORECAST.ETS.CONFINT(B92,$C$5:$C$87,$B$5:$B$87,0.95,1,1) -> 3901743.6
B93: 46599 | D93: =_xlfn.FORECAST.ETS(B93,$C$5:$C$87,$B$5:$B$87,1,1) -> 3193311.7 | E93: =D93-_xlfn.FORECAST.ETS.CONFINT(B93,$C$5:$C$87,$B$5:$B$87,0.95,1,1) -> 2489281.9 | F93: =D93+_xlfn.FORECAST.ETS.CONFINT(B93,$C$5:$C$87,$B$5:$B$87,0.95,1,1) -> 3897341.6
B95: *All figures in thousands of dollars
